{"id":1164,"name":"Rémis Fulgance Dandjinou","type":"Personnes","stats":{"articleCount":8,"countries":["Burkina Faso","Côte d'Ivoire","Gabon","Niger","Saudi Arabia"],"dateRange":{"first":"2018-03-28","last":"2020-08-17"}},"locations":[{"name":"Burkina Faso","lat":12.5,"lng":-1.66667,"country":"Burkina Faso","articleCount":6,"articles":[{"id":"2868","title":"Pouytenga : la sécurité islamique dissoute","date":"2018-03-28","newspaper":"L'Observateur Paalga","country":"Burkina Faso","type":"articles"},{"id":"3576","title":"Hadj 2018 : 8 143 places pour les pèlerins burkinabè","date":"2018-08-02","newspaper":"Sidwaya","country":"Burkina Faso","type":"articles"},{"id":"10146","title":"Sortie porte-parole du gouvernement sur les mosquées : \"Ce sont des propos qui n'apaisent pas le climat social\" (El hadj Abdoul Aziz Rouamba)","date":"2020-05-14","newspaper":"L'Observateur Paalga","country":"Burkina Faso","type":"articles"},{"id":"10148","title":"Propos sur les mosquées : les regrets du ministre Dandjinou","date":"2020-05-17","newspaper":"L'Observateur Paalga","country":"Burkina Faso","type":"articles"},{"id":"10183","title":"Assassinat du grand imam de Djibo : \"Les forces du mal seront traquées\", Roch Marc Christian Kaboré","date":"2020-08-16","newspaper":"Sidwaya","country":"Burkina Faso","type":"articles"},{"id":"10187","title":"Assassinat de l'imam de Djibo : réactions et condamnations tous azimuts","date":"2020-08-17","newspaper":"Le Pays","country":"Burkina Faso","type":"articles"}]},{"name":"Ouagadougou","lat":12.36566,"lng":-1.53388,"country":"Burkina Faso","articleCount":6,"articles":[{"id":"3576","title":"Hadj 2018 : 8 143 places pour les pèlerins burkinabè","date":"2018-08-02","newspaper":"Sidwaya","country":"Burkina Faso","type":"articles"},{"id":"3825","title":"Assassinat du grand imam de Djibo : condamnations et interpellation à Ouagadougou","date":"2020-08-15","newspaper":"Burkina 24","country":"Burkina Faso","type":"articles"},{"id":"10146","title":"Sortie porte-parole du gouvernement sur les mosquées : \"Ce sont des propos qui n'apaisent pas le climat social\" (El hadj Abdoul Aziz Rouamba)","date":"2020-05-14","newspaper":"L'Observateur Paalga","country":"Burkina Faso","type":"articles"},{"id":"10148","title":"Propos sur les mosquées : les regrets du ministre Dandjinou","date":"2020-05-17","newspaper":"L'Observateur Paalga","country":"Burkina Faso","type":"articles"},{"id":"10183","title":"Assassinat du grand imam de Djibo : \"Les forces du mal seront traquées\", Roch Marc Christian Kaboré","date":"2020-08-16","newspaper":"Sidwaya","country":"Burkina Faso","type":"articles"},{"id":"10187","title":"Assassinat de l'imam de Djibo : réactions et condamnations tous azimuts","date":"2020-08-17","newspaper":"Le Pays","country":"Burkina Faso","type":"articles"}]},{"name":"Djibo","lat":14.12526,"lng":-1.6249,"country":"Burkina Faso","articleCount":4,"articles":[{"id":"3576","title":"Hadj 2018 : 8 143 places pour les pèlerins burkinabè","date":"2018-08-02","newspaper":"Sidwaya","country":"Burkina Faso","type":"articles"},{"id":"3825","title":"Assassinat du grand imam de Djibo : condamnations et interpellation à Ouagadougou","date":"2020-08-15","newspaper":"Burkina 24","country":"Burkina Faso","type":"articles"},{"id":"10183","title":"Assassinat du grand imam de Djibo : \"Les forces du mal seront traquées\", Roch Marc Christian Kaboré","date":"2020-08-16","newspaper":"Sidwaya","country":"Burkina Faso","type":"articles"},{"id":"10187","title":"Assassinat de l'imam de Djibo : réactions et condamnations tous azimuts","date":"2020-08-17","newspaper":"Le Pays","country":"Burkina Faso","type":"articles"}]},{"name":"Soum","lat":14.1,"lng":-1.633333,"country":"Burkina Faso","articleCount":3,"articles":[{"id":"3576","title":"Hadj 2018 : 8 143 places pour les pèlerins burkinabè","date":"2018-08-02","newspaper":"Sidwaya","country":"Burkina Faso","type":"articles"},{"id":"10183","title":"Assassinat du grand imam de Djibo : \"Les forces du mal seront traquées\", Roch Marc Christian Kaboré","date":"2020-08-16","newspaper":"Sidwaya","country":"Burkina Faso","type":"articles"},{"id":"10187","title":"Assassinat de l'imam de Djibo : réactions et condamnations tous azimuts","date":"2020-08-17","newspaper":"Le Pays","country":"Burkina Faso","type":"articles"}]},{"name":"Pouytenga","lat":12.25162,"lng":-0.42565,"country":"Burkina Faso","articleCount":2,"articles":[{"id":"2868","title":"Pouytenga : la sécurité islamique dissoute","date":"2018-03-28","newspaper":"L'Observateur Paalga","country":"Burkina Faso","type":"articles"},{"id":"3855","title":"Burkina : dissolution du \"groupe de sécurité islamique\"","date":"2018-03-28","newspaper":"Burkina 24","country":"Burkina Faso","type":"articles"}]},{"name":"Bobo-Dioulasso","lat":11.17715,"lng":-4.2979,"country":"Burkina Faso","articleCount":1,"articles":[{"id":"3576","title":"Hadj 2018 : 8 143 places pour les pèlerins burkinabè","date":"2018-08-02","newspaper":"Sidwaya","country":"Burkina Faso","type":"articles"}]},{"name":"Côte d'Ivoire","lat":8.0,"lng":-5.5,"country":"Côte d'Ivoire","articleCount":1,"articles":[{"id":"3576","title":"Hadj 2018 : 8 143 places pour les pèlerins burkinabè","date":"2018-08-02","newspaper":"Sidwaya","country":"Burkina Faso","type":"articles"}]},{"name":"Gabon","lat":-1.0,"lng":11.75,"country":"Gabon","articleCount":1,"articles":[{"id":"3576","title":"Hadj 2018 : 8 143 places pour les pèlerins burkinabè","date":"2018-08-02","newspaper":"Sidwaya","country":"Burkina Faso","type":"articles"}]},{"name":"Arabie saoudite","lat":25.0,"lng":45.0,"country":"Saudi Arabia","articleCount":1,"articles":[{"id":"3576","title":"Hadj 2018 : 8 143 places pour les pèlerins burkinabè","date":"2018-08-02","newspaper":"Sidwaya","country":"Burkina Faso","type":"articles"}]},{"name":"Kongoussi","lat":13.32583,"lng":-1.53472,"country":"Burkina Faso","articleCount":1,"articles":[{"id":"10187","title":"Assassinat de l'imam de Djibo : réactions et condamnations tous azimuts","date":"2020-08-17","newspaper":"Le Pays","country":"Burkina Faso","type":"articles"}]},{"name":"Sahel","lat":14.474672,"lng":13.511696,"country":"Niger","articleCount":1,"articles":[{"id":"10187","title":"Assassinat de l'imam de Djibo : réactions et condamnations tous azimuts","date":"2020-08-17","newspaper":"Le Pays","country":"Burkina Faso","type":"articles"}]}]}