{"id":1402,"name":"Joachim Marie Florès Vignon Apithy","type":"Personnes","stats":{"articleCount":15,"countries":["Benin","Saudi Arabia"],"dateRange":{"first":"2016-07-06","last":"2018-06-18"}},"locations":[{"name":"Porto-Novo","lat":6.49646,"lng":2.60359,"country":"Benin","articleCount":15,"articles":[{"id":"4562","title":"Ramadan 2017 : sous le signe de la repentance à Porto-Novo","date":"2017-06-25","newspaper":"La Nation","country":"Benin","type":"articles"},{"id":"4588","title":"Fête de Tabaski 2017 : les musulmans de Porto-Novo invités à tuer le mouton avec respect","date":"2017-09-01","newspaper":"La Nation","country":"Benin","type":"articles"},{"id":"7154","title":"Pour risque de trouble à l'ordre public à Porto-Novo : la mosquée centrale Sofwa de Sèdjèko fermée","date":"2016-10-21","newspaper":"La Nation","country":"Benin","type":"articles"},{"id":"7794","title":"Fête de l'Aïd-el-Fitr 2016 : l'iman de Porto-Novo appelle ses fidèles à la solidarité","date":"2016-07-07","newspaper":"La Nation","country":"Benin","type":"articles"},{"id":"7795","title":"Fête de l'Aïd-el-Fitr 2016 : Ahamdiyya Bénin partage la joie avec des ménages pauvres de l'Ouémé","date":"2016-07-07","newspaper":"La Nation","country":"Benin","type":"articles"},{"id":"7825","title":"Tabaski 2016 : les musulmans de Porto-Novo invités à marcher dans les pas d'Allah","date":"2016-09-13","newspaper":"La Nation","country":"Benin","type":"articles"},{"id":"7945","title":"Sur décision du ministère chargé de l'Intérieur : la mosquée Sofwath de Porto-Novo réouverte","date":"2017-06-19","newspaper":"La Nation","country":"Benin","type":"articles"},{"id":"9119","title":"Distribution de vivres aux pauvres : Ahmadiyya partage la joie du Ramadan dans l'Ouémé","date":"2017-06-23","newspaper":"La Nation","country":"Benin","type":"articles"},{"id":"9196","title":"Congrès ordinaire de l'Uib demain à Porto-Novo : \"Pas d’exclusion\", dixit Adégbola","date":"2017-05-19","newspaper":"Matin Libre","country":"Benin","type":"articles"},{"id":"23440","title":"Ramadan 2018 : Me Adrien Houngbédji à la grande prière musulmane à Porto-Novo","date":"2018-06-15","newspaper":"La Nation","country":"Benin","type":"articles"},{"id":"45991","title":"Célébration de la fête du Ramadan : exhortation à la réconciliation et à l'union à Porto-Novo","date":"2017-06-27","newspaper":"La Nation","country":"Benin","type":"articles"},{"id":"46002","title":"Célébration de l'Aïd el-fitr : Me Adrien Houngbédji rehausse la prière musulmane à Porto-Novo","date":"2018-06-18","newspaper":"La Nation","country":"Benin","type":"articles"},{"id":"46005","title":"Célébration de l'Aïd el-Kébir : les musulmans de Porto-Novo renouvellent leur foi à Allah","date":"2017-09-04","newspaper":"La Nation","country":"Benin","type":"articles"},{"id":"75896","title":"Adrien Houngbédji en communion de prière avec la communauté musulmane pour le ramadan","date":"2018-06-16","newspaper":"Agence Bénin Presse","country":"Benin","type":"articles"},{"id":"75905","title":"Le préfet Apithy et l’imam Ouzéifa appellent la communauté musulmane de Porto-Novo à agir dans le sens de la paix à l’occasion de l’Aïd-El-Fitr","date":"2016-07-06","newspaper":"Agence Bénin Presse","country":"Benin","type":"articles"}]},{"name":"Ouémé","lat":6.5,"lng":2.6,"country":"Benin","articleCount":12,"articles":[{"id":"4562","title":"Ramadan 2017 : sous le signe de la repentance à Porto-Novo","date":"2017-06-25","newspaper":"La Nation","country":"Benin","type":"articles"},{"id":"4588","title":"Fête de Tabaski 2017 : les musulmans de Porto-Novo invités à tuer le mouton avec respect","date":"2017-09-01","newspaper":"La Nation","country":"Benin","type":"articles"},{"id":"7154","title":"Pour risque de trouble à l'ordre public à Porto-Novo : la mosquée centrale Sofwa de Sèdjèko fermée","date":"2016-10-21","newspaper":"La Nation","country":"Benin","type":"articles"},{"id":"7794","title":"Fête de l'Aïd-el-Fitr 2016 : l'iman de Porto-Novo appelle ses fidèles à la solidarité","date":"2016-07-07","newspaper":"La Nation","country":"Benin","type":"articles"},{"id":"7795","title":"Fête de l'Aïd-el-Fitr 2016 : Ahamdiyya Bénin partage la joie avec des ménages pauvres de l'Ouémé","date":"2016-07-07","newspaper":"La Nation","country":"Benin","type":"articles"},{"id":"7825","title":"Tabaski 2016 : les musulmans de Porto-Novo invités à marcher dans les pas d'Allah","date":"2016-09-13","newspaper":"La Nation","country":"Benin","type":"articles"},{"id":"7945","title":"Sur décision du ministère chargé de l'Intérieur : la mosquée Sofwath de Porto-Novo réouverte","date":"2017-06-19","newspaper":"La Nation","country":"Benin","type":"articles"},{"id":"23440","title":"Ramadan 2018 : Me Adrien Houngbédji à la grande prière musulmane à Porto-Novo","date":"2018-06-15","newspaper":"La Nation","country":"Benin","type":"articles"},{"id":"45991","title":"Célébration de la fête du Ramadan : exhortation à la réconciliation et à l'union à Porto-Novo","date":"2017-06-27","newspaper":"La Nation","country":"Benin","type":"articles"},{"id":"46002","title":"Célébration de l'Aïd el-fitr : Me Adrien Houngbédji rehausse la prière musulmane à Porto-Novo","date":"2018-06-18","newspaper":"La Nation","country":"Benin","type":"articles"},{"id":"46005","title":"Célébration de l'Aïd el-Kébir : les musulmans de Porto-Novo renouvellent leur foi à Allah","date":"2017-09-04","newspaper":"La Nation","country":"Benin","type":"articles"},{"id":"75905","title":"Le préfet Apithy et l’imam Ouzéifa appellent la communauté musulmane de Porto-Novo à agir dans le sens de la paix à l’occasion de l’Aïd-El-Fitr","date":"2016-07-06","newspaper":"Agence Bénin Presse","country":"Benin","type":"articles"}]},{"name":"Bénin","lat":9.5,"lng":2.25,"country":"Benin","articleCount":9,"articles":[{"id":"4562","title":"Ramadan 2017 : sous le signe de la repentance à Porto-Novo","date":"2017-06-25","newspaper":"La Nation","country":"Benin","type":"articles"},{"id":"4588","title":"Fête de Tabaski 2017 : les musulmans de Porto-Novo invités à tuer le mouton avec respect","date":"2017-09-01","newspaper":"La Nation","country":"Benin","type":"articles"},{"id":"7794","title":"Fête de l'Aïd-el-Fitr 2016 : l'iman de Porto-Novo appelle ses fidèles à la solidarité","date":"2016-07-07","newspaper":"La Nation","country":"Benin","type":"articles"},{"id":"9119","title":"Distribution de vivres aux pauvres : Ahmadiyya partage la joie du Ramadan dans l'Ouémé","date":"2017-06-23","newspaper":"La Nation","country":"Benin","type":"articles"},{"id":"9196","title":"Congrès ordinaire de l'Uib demain à Porto-Novo : \"Pas d’exclusion\", dixit Adégbola","date":"2017-05-19","newspaper":"Matin Libre","country":"Benin","type":"articles"},{"id":"23440","title":"Ramadan 2018 : Me Adrien Houngbédji à la grande prière musulmane à Porto-Novo","date":"2018-06-15","newspaper":"La Nation","country":"Benin","type":"articles"},{"id":"45991","title":"Célébration de la fête du Ramadan : exhortation à la réconciliation et à l'union à Porto-Novo","date":"2017-06-27","newspaper":"La Nation","country":"Benin","type":"articles"},{"id":"46002","title":"Célébration de l'Aïd el-fitr : Me Adrien Houngbédji rehausse la prière musulmane à Porto-Novo","date":"2018-06-18","newspaper":"La Nation","country":"Benin","type":"articles"},{"id":"46005","title":"Célébration de l'Aïd el-Kébir : les musulmans de Porto-Novo renouvellent leur foi à Allah","date":"2017-09-04","newspaper":"La Nation","country":"Benin","type":"articles"}]},{"name":"La Mecque","lat":21.4225,"lng":39.826111,"country":"Saudi Arabia","articleCount":2,"articles":[{"id":"4588","title":"Fête de Tabaski 2017 : les musulmans de Porto-Novo invités à tuer le mouton avec respect","date":"2017-09-01","newspaper":"La Nation","country":"Benin","type":"articles"},{"id":"46005","title":"Célébration de l'Aïd el-Kébir : les musulmans de Porto-Novo renouvellent leur foi à Allah","date":"2017-09-04","newspaper":"La Nation","country":"Benin","type":"articles"}]},{"name":"Mosquée centrale de Porto-Novo","lat":6.470333,"lng":2.626611,"country":"Benin","articleCount":2,"articles":[{"id":"7794","title":"Fête de l'Aïd-el-Fitr 2016 : l'iman de Porto-Novo appelle ses fidèles à la solidarité","date":"2016-07-07","newspaper":"La Nation","country":"Benin","type":"articles"},{"id":"75896","title":"Adrien Houngbédji en communion de prière avec la communauté musulmane pour le ramadan","date":"2018-06-16","newspaper":"Agence Bénin Presse","country":"Benin","type":"articles"}]},{"name":"Adjarra","lat":6.53445,"lng":2.66833,"country":"Benin","articleCount":2,"articles":[{"id":"7795","title":"Fête de l'Aïd-el-Fitr 2016 : Ahamdiyya Bénin partage la joie avec des ménages pauvres de l'Ouémé","date":"2016-07-07","newspaper":"La Nation","country":"Benin","type":"articles"},{"id":"9119","title":"Distribution de vivres aux pauvres : Ahmadiyya partage la joie du Ramadan dans l'Ouémé","date":"2017-06-23","newspaper":"La Nation","country":"Benin","type":"articles"}]},{"name":"Avrankou","lat":0,"lng":0,"country":"Unknown","articleCount":2,"articles":[{"id":"7795","title":"Fête de l'Aïd-el-Fitr 2016 : Ahamdiyya Bénin partage la joie avec des ménages pauvres de l'Ouémé","date":"2016-07-07","newspaper":"La Nation","country":"Benin","type":"articles"},{"id":"9119","title":"Distribution de vivres aux pauvres : Ahmadiyya partage la joie du Ramadan dans l'Ouémé","date":"2017-06-23","newspaper":"La Nation","country":"Benin","type":"articles"}]},{"name":"mosquée centrale Sofwa de Sèdjèko","lat":0,"lng":0,"country":"Unknown","articleCount":1,"articles":[{"id":"7154","title":"Pour risque de trouble à l'ordre public à Porto-Novo : la mosquée centrale Sofwa de Sèdjèko fermée","date":"2016-10-21","newspaper":"La Nation","country":"Benin","type":"articles"}]}]}