{"id":46262,"name":"Robert Guéï","type":"Personnes","stats":{"articleCount":28,"countries":["Algeria","Angola","Benin","Burkina Faso","Canada","Côte d'Ivoire","France","Germany","Liberia","Mali","Nigeria","Russia","Rwanda","Saudi Arabia","Senegal","Sierra Leone","Switzerland","Togo","United Kingdom","United States of America"],"dateRange":{"first":"1994-01-28","last":"2017-08-04"}},"locations":[{"name":"Côte d'Ivoire","lat":8.0,"lng":-5.5,"country":"Côte d'Ivoire","articleCount":25,"articles":[{"id":"46399","title":"Forum pour la réconciliation nationale","date":"2001-10-24","newspaper":"Notre Voie","country":"Côte d'Ivoire","type":"articles"},{"id":"46447","title":"Agora : Laurent Gbagbo et la laïcité de l'Etat","date":"2003-10-06","newspaper":"Notre Voie","country":"Côte d'Ivoire","type":"articles"},{"id":"46604","title":"Fête de la lumière à Kapélé (Korhogo) / L'imam Sanogo : \"Nous sommes avec Gbagbo\"","date":"2010-05-25","newspaper":"Notre Voie","country":"Côte d'Ivoire","type":"articles"},{"id":"46726","title":"Réconciliation nationale : ceux qui vont faire échouer Banny","date":"2011-09-08","newspaper":"Notre Voie","country":"Côte d'Ivoire","type":"articles"},{"id":"48255","title":"Alassane, la charte et les deux imams","date":"2000-06-09","newspaper":"Notre Voie","country":"Côte d'Ivoire","type":"articles"},{"id":"48335","title":"Affaire \"Il n'y a pas un nord musulman contre un sud chrétien\" de Soro : or donc la rébellion reposait sur des arguments fallacieux","date":"2017-08-04","newspaper":"Notre Voie","country":"Côte d'Ivoire","type":"articles"},{"id":"48503","title":"L'imam Sékou Sylla (Petite mosquée de la Riviera II) : \"Que Guéï arrête de diaboliser l'islam\"","date":"2000-06-30","newspaper":"Le Patriote","country":"Côte d'Ivoire","type":"articles"},{"id":"48507","title":"Tracasseries contre la communauté musulmane : Déon Georges veut arrêter Koudouss et quatre grands imams","date":"2000-08-23","newspaper":"Le Patriote","country":"Côte d'Ivoire","type":"articles"},{"id":"48583","title":"Fête de Ramadan : les musulmans de Yopougon ont prié pour la paix en Côte d'Ivoire","date":"2000-01-10","newspaper":"Le Patriote","country":"Côte d'Ivoire","type":"articles"},{"id":"48584","title":"Conseil consultatif du COSIM à la grande mosquée de la Riviera : les musulmans déçus de Guéï et du CNSP","date":"2000-08-14","newspaper":"Le Patriote","country":"Côte d'Ivoire","type":"articles"},{"id":"48585","title":"Nuit de la jeunesse musulmane : prière pour la paix en Côte d'Ivoire","date":"2000-08-21","newspaper":"Le Patriote","country":"Côte d'Ivoire","type":"articles"},{"id":"48587","title":"Convocation des Imams par le Colonel Déon : la grande colère des musulmans","date":"2000-08-25","newspaper":"Le Patriote","country":"Côte d'Ivoire","type":"articles"},{"id":"48588","title":"Rencontre avec les Imams : Guéi promet la fin du harcèlement contre les musulmans","date":"2000-08-30","newspaper":"Le Patriote","country":"Côte d'Ivoire","type":"articles"},{"id":"48594","title":"Présidentielle 2000 : l'appel du COSIM aux fidèles musulmans","date":"2000-10-21","newspaper":"Le Patriote","country":"Côte d'Ivoire","type":"articles"},{"id":"48630","title":"Rapport accablant sur la Côte d'Ivoire : Human Rights Watch dénonce les violences ethniques et religieuses","date":"2000-12-22","newspaper":"Le Patriote","country":"Côte d'Ivoire","type":"articles"},{"id":"48669","title":"Réconciliation nationale : Gbagbo et les musulmans face à face enfin!","date":"2001-06-09","newspaper":"Le Patriote","country":"Côte d'Ivoire","type":"articles"},{"id":"48699","title":"M. Benoît Scheuer (Réalisateur du film Côte d'Ivoire, poudrière identitaire) persiste et signe : \"Il y a des tentations génocidaires en Côte d'Ivoire\"","date":"2001-07-19","newspaper":"Le Patriote","country":"Côte d'Ivoire","type":"articles"},{"id":"48717","title":"Résolution de la crise socio-politique en Côte d'Ivoire : le CNI demande l'implication de la France","date":"2001-12-04","newspaper":"Le Patriote","country":"Côte d'Ivoire","type":"articles"},{"id":"62698","title":"Alassane Drame Ouattara a-t-il un avenir politique en Côte d'Ivoire?","date":"1994-01-28","newspaper":"Le Nouvel Horizon","country":"Côte d'Ivoire","type":"articles"},{"id":"63782","title":"À l'inauguration hier de la mosquée d'Akouédo : Bédié pour l'unité des musulmans","date":"1994-08-20","newspaper":"Fraternité Matin","country":"Côte d'Ivoire","type":"articles"},{"id":"63981","title":"Événements à la mosquée de Banco II (Abobo) : les résultats de la commission d'enquête","date":"1994-08-23","newspaper":"Fraternité Matin","country":"Côte d'Ivoire","type":"articles"},{"id":"64679","title":"Changement de régime politique en Côte d'Ivoire : les religieux invités à éteindre les passions","date":"1999-12-30","newspaper":"Fraternité Matin","country":"Côte d'Ivoire","type":"articles"},{"id":"64680","title":"Changement de régime politique en Côte d'Ivoire : chapelles et mosquées au village","date":"1999-12-30","newspaper":"Fraternité Matin","country":"Côte d'Ivoire","type":"articles"},{"id":"73682","title":"Aboubacar Fofana (président du Conseil supérieur des Imams) : \"En Côte d'Ivoire des pasteurs sont marchands d'armes\"","date":"2003-08-27","newspaper":"Le Patriote","country":"Côte d'Ivoire","type":"articles"},{"id":"74352","title":"Crise post-électorale / Un imam sort de sa réserve : \"Cessons de nous maudire en croyant maudire autrui\"","date":"2011-02-03","newspaper":"Le Jour Plus","country":"Côte d'Ivoire","type":"articles"}]},{"name":"Abidjan","lat":5.35444,"lng":-4.00167,"country":"Côte d'Ivoire","articleCount":8,"articles":[{"id":"48587","title":"Convocation des Imams par le Colonel Déon : la grande colère des musulmans","date":"2000-08-25","newspaper":"Le Patriote","country":"Côte d'Ivoire","type":"articles"},{"id":"48594","title":"Présidentielle 2000 : l'appel du COSIM aux fidèles musulmans","date":"2000-10-21","newspaper":"Le Patriote","country":"Côte d'Ivoire","type":"articles"},{"id":"48630","title":"Rapport accablant sur la Côte d'Ivoire : Human Rights Watch dénonce les violences ethniques et religieuses","date":"2000-12-22","newspaper":"Le Patriote","country":"Côte d'Ivoire","type":"articles"},{"id":"48669","title":"Réconciliation nationale : Gbagbo et les musulmans face à face enfin!","date":"2001-06-09","newspaper":"Le Patriote","country":"Côte d'Ivoire","type":"articles"},{"id":"63981","title":"Événements à la mosquée de Banco II (Abobo) : les résultats de la commission d'enquête","date":"1994-08-23","newspaper":"Fraternité Matin","country":"Côte d'Ivoire","type":"articles"},{"id":"64679","title":"Changement de régime politique en Côte d'Ivoire : les religieux invités à éteindre les passions","date":"1999-12-30","newspaper":"Fraternité Matin","country":"Côte d'Ivoire","type":"articles"},{"id":"73682","title":"Aboubacar Fofana (président du Conseil supérieur des Imams) : \"En Côte d'Ivoire des pasteurs sont marchands d'armes\"","date":"2003-08-27","newspaper":"Le Patriote","country":"Côte d'Ivoire","type":"articles"},{"id":"74352","title":"Crise post-électorale / Un imam sort de sa réserve : \"Cessons de nous maudire en croyant maudire autrui\"","date":"2011-02-03","newspaper":"Le Jour Plus","country":"Côte d'Ivoire","type":"articles"}]},{"name":"France","lat":46.0,"lng":2.0,"country":"France","articleCount":6,"articles":[{"id":"46726","title":"Réconciliation nationale : ceux qui vont faire échouer Banny","date":"2011-09-08","newspaper":"Notre Voie","country":"Côte d'Ivoire","type":"articles"},{"id":"48335","title":"Affaire \"Il n'y a pas un nord musulman contre un sud chrétien\" de Soro : or donc la rébellion reposait sur des arguments fallacieux","date":"2017-08-04","newspaper":"Notre Voie","country":"Côte d'Ivoire","type":"articles"},{"id":"48630","title":"Rapport accablant sur la Côte d'Ivoire : Human Rights Watch dénonce les violences ethniques et religieuses","date":"2000-12-22","newspaper":"Le Patriote","country":"Côte d'Ivoire","type":"articles"},{"id":"48717","title":"Résolution de la crise socio-politique en Côte d'Ivoire : le CNI demande l'implication de la France","date":"2001-12-04","newspaper":"Le Patriote","country":"Côte d'Ivoire","type":"articles"},{"id":"62698","title":"Alassane Drame Ouattara a-t-il un avenir politique en Côte d'Ivoire?","date":"1994-01-28","newspaper":"Le Nouvel Horizon","country":"Côte d'Ivoire","type":"articles"},{"id":"74352","title":"Crise post-électorale / Un imam sort de sa réserve : \"Cessons de nous maudire en croyant maudire autrui\"","date":"2011-02-03","newspaper":"Le Jour Plus","country":"Côte d'Ivoire","type":"articles"}]},{"name":"La Mecque","lat":21.4225,"lng":39.826111,"country":"Saudi Arabia","articleCount":5,"articles":[{"id":"46447","title":"Agora : Laurent Gbagbo et la laïcité de l'Etat","date":"2003-10-06","newspaper":"Notre Voie","country":"Côte d'Ivoire","type":"articles"},{"id":"48503","title":"L'imam Sékou Sylla (Petite mosquée de la Riviera II) : \"Que Guéï arrête de diaboliser l'islam\"","date":"2000-06-30","newspaper":"Le Patriote","country":"Côte d'Ivoire","type":"articles"},{"id":"48672","title":"Le pouvoir veut-il vraiment la réconciliation? Rencontre Gbagbo-musulmans : ce qui n'a pas été révélé par la presse!","date":"2001-06-14","newspaper":"Le Patriote","country":"Côte d'Ivoire","type":"articles"},{"id":"63782","title":"À l'inauguration hier de la mosquée d'Akouédo : Bédié pour l'unité des musulmans","date":"1994-08-20","newspaper":"Fraternité Matin","country":"Côte d'Ivoire","type":"articles"},{"id":"74083","title":"Rentré hier de la Mecque : Mabri veut les élections en février","date":"2009-12-02","newspaper":"Le Jour Plus","country":"Côte d'Ivoire","type":"articles"}]},{"name":"États-Unis","lat":39.76,"lng":-98.5,"country":"United States of America","articleCount":5,"articles":[{"id":"46726","title":"Réconciliation nationale : ceux qui vont faire échouer Banny","date":"2011-09-08","newspaper":"Notre Voie","country":"Côte d'Ivoire","type":"articles"},{"id":"48594","title":"Présidentielle 2000 : l'appel du COSIM aux fidèles musulmans","date":"2000-10-21","newspaper":"Le Patriote","country":"Côte d'Ivoire","type":"articles"},{"id":"62698","title":"Alassane Drame Ouattara a-t-il un avenir politique en Côte d'Ivoire?","date":"1994-01-28","newspaper":"Le Nouvel Horizon","country":"Côte d'Ivoire","type":"articles"},{"id":"73682","title":"Aboubacar Fofana (président du Conseil supérieur des Imams) : \"En Côte d'Ivoire des pasteurs sont marchands d'armes\"","date":"2003-08-27","newspaper":"Le Patriote","country":"Côte d'Ivoire","type":"articles"},{"id":"74352","title":"Crise post-électorale / Un imam sort de sa réserve : \"Cessons de nous maudire en croyant maudire autrui\"","date":"2011-02-03","newspaper":"Le Jour Plus","country":"Côte d'Ivoire","type":"articles"}]},{"name":"Grand-Bassam","lat":5.2118,"lng":-3.73884,"country":"Côte d'Ivoire","articleCount":4,"articles":[{"id":"31883","title":"Grand Bassam : les musulmans dans l'espace francophone","date":"2000-08-08","newspaper":"Fraternité Matin","country":"Côte d'Ivoire","type":"articles"},{"id":"46726","title":"Réconciliation nationale : ceux qui vont faire échouer Banny","date":"2011-09-08","newspaper":"Notre Voie","country":"Côte d'Ivoire","type":"articles"},{"id":"48669","title":"Réconciliation nationale : Gbagbo et les musulmans face à face enfin!","date":"2001-06-09","newspaper":"Le Patriote","country":"Côte d'Ivoire","type":"articles"},{"id":"74352","title":"Crise post-électorale / Un imam sort de sa réserve : \"Cessons de nous maudire en croyant maudire autrui\"","date":"2011-02-03","newspaper":"Le Jour Plus","country":"Côte d'Ivoire","type":"articles"}]},{"name":"Paris","lat":48.85341,"lng":2.3488,"country":"France","articleCount":4,"articles":[{"id":"46399","title":"Forum pour la réconciliation nationale","date":"2001-10-24","newspaper":"Notre Voie","country":"Côte d'Ivoire","type":"articles"},{"id":"46447","title":"Agora : Laurent Gbagbo et la laïcité de l'Etat","date":"2003-10-06","newspaper":"Notre Voie","country":"Côte d'Ivoire","type":"articles"},{"id":"62698","title":"Alassane Drame Ouattara a-t-il un avenir politique en Côte d'Ivoire?","date":"1994-01-28","newspaper":"Le Nouvel Horizon","country":"Côte d'Ivoire","type":"articles"},{"id":"74352","title":"Crise post-électorale / Un imam sort de sa réserve : \"Cessons de nous maudire en croyant maudire autrui\"","date":"2011-02-03","newspaper":"Le Jour Plus","country":"Côte d'Ivoire","type":"articles"}]},{"name":"Yopougon","lat":5.316667,"lng":-4.066667,"country":"Côte d'Ivoire","articleCount":4,"articles":[{"id":"48583","title":"Fête de Ramadan : les musulmans de Yopougon ont prié pour la paix en Côte d'Ivoire","date":"2000-01-10","newspaper":"Le Patriote","country":"Côte d'Ivoire","type":"articles"},{"id":"48594","title":"Présidentielle 2000 : l'appel du COSIM aux fidèles musulmans","date":"2000-10-21","newspaper":"Le Patriote","country":"Côte d'Ivoire","type":"articles"},{"id":"48630","title":"Rapport accablant sur la Côte d'Ivoire : Human Rights Watch dénonce les violences ethniques et religieuses","date":"2000-12-22","newspaper":"Le Patriote","country":"Côte d'Ivoire","type":"articles"},{"id":"48672","title":"Le pouvoir veut-il vraiment la réconciliation? Rencontre Gbagbo-musulmans : ce qui n'a pas été révélé par la presse!","date":"2001-06-14","newspaper":"Le Patriote","country":"Côte d'Ivoire","type":"articles"}]},{"name":"Abobo","lat":5.418889,"lng":-4.020556,"country":"Côte d'Ivoire","articleCount":4,"articles":[{"id":"48587","title":"Convocation des Imams par le Colonel Déon : la grande colère des musulmans","date":"2000-08-25","newspaper":"Le Patriote","country":"Côte d'Ivoire","type":"articles"},{"id":"48630","title":"Rapport accablant sur la Côte d'Ivoire : Human Rights Watch dénonce les violences ethniques et religieuses","date":"2000-12-22","newspaper":"Le Patriote","country":"Côte d'Ivoire","type":"articles"},{"id":"63782","title":"À l'inauguration hier de la mosquée d'Akouédo : Bédié pour l'unité des musulmans","date":"1994-08-20","newspaper":"Fraternité Matin","country":"Côte d'Ivoire","type":"articles"},{"id":"63981","title":"Événements à la mosquée de Banco II (Abobo) : les résultats de la commission d'enquête","date":"1994-08-23","newspaper":"Fraternité Matin","country":"Côte d'Ivoire","type":"articles"}]},{"name":"Korhogo","lat":9.457778,"lng":-5.629444,"country":"Côte d'Ivoire","articleCount":3,"articles":[{"id":"46604","title":"Fête de la lumière à Kapélé (Korhogo) / L'imam Sanogo : \"Nous sommes avec Gbagbo\"","date":"2010-05-25","newspaper":"Notre Voie","country":"Côte d'Ivoire","type":"articles"},{"id":"48587","title":"Convocation des Imams par le Colonel Déon : la grande colère des musulmans","date":"2000-08-25","newspaper":"Le Patriote","country":"Côte d'Ivoire","type":"articles"},{"id":"73682","title":"Aboubacar Fofana (président du Conseil supérieur des Imams) : \"En Côte d'Ivoire des pasteurs sont marchands d'armes\"","date":"2003-08-27","newspaper":"Le Patriote","country":"Côte d'Ivoire","type":"articles"}]},{"name":"Mali","lat":18.0,"lng":-2.0,"country":"Mali","articleCount":3,"articles":[{"id":"48503","title":"L'imam Sékou Sylla (Petite mosquée de la Riviera II) : \"Que Guéï arrête de diaboliser l'islam\"","date":"2000-06-30","newspaper":"Le Patriote","country":"Côte d'Ivoire","type":"articles"},{"id":"48587","title":"Convocation des Imams par le Colonel Déon : la grande colère des musulmans","date":"2000-08-25","newspaper":"Le Patriote","country":"Côte d'Ivoire","type":"articles"},{"id":"64679","title":"Changement de régime politique en Côte d'Ivoire : les religieux invités à éteindre les passions","date":"1999-12-30","newspaper":"Fraternité Matin","country":"Côte d'Ivoire","type":"articles"}]},{"name":"Aghien","lat":5.388123,"lng":-3.999984,"country":"Côte d'Ivoire","articleCount":3,"articles":[{"id":"48503","title":"L'imam Sékou Sylla (Petite mosquée de la Riviera II) : \"Que Guéï arrête de diaboliser l'islam\"","date":"2000-06-30","newspaper":"Le Patriote","country":"Côte d'Ivoire","type":"articles"},{"id":"48584","title":"Conseil consultatif du COSIM à la grande mosquée de la Riviera : les musulmans déçus de Guéï et du CNSP","date":"2000-08-14","newspaper":"Le Patriote","country":"Côte d'Ivoire","type":"articles"},{"id":"48587","title":"Convocation des Imams par le Colonel Déon : la grande colère des musulmans","date":"2000-08-25","newspaper":"Le Patriote","country":"Côte d'Ivoire","type":"articles"}]},{"name":"Burkina Faso","lat":12.5,"lng":-1.66667,"country":"Burkina Faso","articleCount":3,"articles":[{"id":"48503","title":"L'imam Sékou Sylla (Petite mosquée de la Riviera II) : \"Que Guéï arrête de diaboliser l'islam\"","date":"2000-06-30","newspaper":"Le Patriote","country":"Côte d'Ivoire","type":"articles"},{"id":"48587","title":"Convocation des Imams par le Colonel Déon : la grande colère des musulmans","date":"2000-08-25","newspaper":"Le Patriote","country":"Côte d'Ivoire","type":"articles"},{"id":"62698","title":"Alassane Drame Ouattara a-t-il un avenir politique en Côte d'Ivoire?","date":"1994-01-28","newspaper":"Le Nouvel Horizon","country":"Côte d'Ivoire","type":"articles"}]},{"name":"Yamoussoukro","lat":6.816111,"lng":-5.274167,"country":"Côte d'Ivoire","articleCount":3,"articles":[{"id":"48587","title":"Convocation des Imams par le Colonel Déon : la grande colère des musulmans","date":"2000-08-25","newspaper":"Le Patriote","country":"Côte d'Ivoire","type":"articles"},{"id":"62698","title":"Alassane Drame Ouattara a-t-il un avenir politique en Côte d'Ivoire?","date":"1994-01-28","newspaper":"Le Nouvel Horizon","country":"Côte d'Ivoire","type":"articles"},{"id":"74352","title":"Crise post-électorale / Un imam sort de sa réserve : \"Cessons de nous maudire en croyant maudire autrui\"","date":"2011-02-03","newspaper":"Le Jour Plus","country":"Côte d'Ivoire","type":"articles"}]},{"name":"Port-Bouët","lat":5.266667,"lng":-3.9,"country":"Côte d'Ivoire","articleCount":3,"articles":[{"id":"48594","title":"Présidentielle 2000 : l'appel du COSIM aux fidèles musulmans","date":"2000-10-21","newspaper":"Le Patriote","country":"Côte d'Ivoire","type":"articles"},{"id":"62698","title":"Alassane Drame Ouattara a-t-il un avenir politique en Côte d'Ivoire?","date":"1994-01-28","newspaper":"Le Nouvel Horizon","country":"Côte d'Ivoire","type":"articles"},{"id":"74083","title":"Rentré hier de la Mecque : Mabri veut les élections en février","date":"2009-12-02","newspaper":"Le Jour Plus","country":"Côte d'Ivoire","type":"articles"}]},{"name":"Bouaké","lat":7.68333,"lng":-5.03306,"country":"Côte d'Ivoire","articleCount":2,"articles":[{"id":"46726","title":"Réconciliation nationale : ceux qui vont faire échouer Banny","date":"2011-09-08","newspaper":"Notre Voie","country":"Côte d'Ivoire","type":"articles"},{"id":"73682","title":"Aboubacar Fofana (président du Conseil supérieur des Imams) : \"En Côte d'Ivoire des pasteurs sont marchands d'armes\"","date":"2003-08-27","newspaper":"Le Patriote","country":"Côte d'Ivoire","type":"articles"}]},{"name":"Cocody","lat":5.35,"lng":-3.9666666666667,"country":"Côte d'Ivoire","articleCount":2,"articles":[{"id":"48335","title":"Affaire \"Il n'y a pas un nord musulman contre un sud chrétien\" de Soro : or donc la rébellion reposait sur des arguments fallacieux","date":"2017-08-04","newspaper":"Notre Voie","country":"Côte d'Ivoire","type":"articles"},{"id":"48503","title":"L'imam Sékou Sylla (Petite mosquée de la Riviera II) : \"Que Guéï arrête de diaboliser l'islam\"","date":"2000-06-30","newspaper":"Le Patriote","country":"Côte d'Ivoire","type":"articles"}]},{"name":"Liberia","lat":6.533333,"lng":-9.75,"country":"Liberia","articleCount":2,"articles":[{"id":"48503","title":"L'imam Sékou Sylla (Petite mosquée de la Riviera II) : \"Que Guéï arrête de diaboliser l'islam\"","date":"2000-06-30","newspaper":"Le Patriote","country":"Côte d'Ivoire","type":"articles"},{"id":"73682","title":"Aboubacar Fofana (président du Conseil supérieur des Imams) : \"En Côte d'Ivoire des pasteurs sont marchands d'armes\"","date":"2003-08-27","newspaper":"Le Patriote","country":"Côte d'Ivoire","type":"articles"}]},{"name":"Sierra Leone","lat":8.5,"lng":-12.1,"country":"Sierra Leone","articleCount":2,"articles":[{"id":"48503","title":"L'imam Sékou Sylla (Petite mosquée de la Riviera II) : \"Que Guéï arrête de diaboliser l'islam\"","date":"2000-06-30","newspaper":"Le Patriote","country":"Côte d'Ivoire","type":"articles"},{"id":"73682","title":"Aboubacar Fofana (président du Conseil supérieur des Imams) : \"En Côte d'Ivoire des pasteurs sont marchands d'armes\"","date":"2003-08-27","newspaper":"Le Patriote","country":"Côte d'Ivoire","type":"articles"}]},{"name":"Adjamé","lat":5.3648,"lng":-4.02366,"country":"Côte d'Ivoire","articleCount":2,"articles":[{"id":"48503","title":"L'imam Sékou Sylla (Petite mosquée de la Riviera II) : \"Que Guéï arrête de diaboliser l'islam\"","date":"2000-06-30","newspaper":"Le Patriote","country":"Côte d'Ivoire","type":"articles"},{"id":"48587","title":"Convocation des Imams par le Colonel Déon : la grande colère des musulmans","date":"2000-08-25","newspaper":"Le Patriote","country":"Côte d'Ivoire","type":"articles"}]},{"name":"Riviera Golf","lat":0,"lng":0,"country":"Unknown","articleCount":2,"articles":[{"id":"48503","title":"L'imam Sékou Sylla (Petite mosquée de la Riviera II) : \"Que Guéï arrête de diaboliser l'islam\"","date":"2000-06-30","newspaper":"Le Patriote","country":"Côte d'Ivoire","type":"articles"},{"id":"48507","title":"Tracasseries contre la communauté musulmane : Déon Georges veut arrêter Koudouss et quatre grands imams","date":"2000-08-23","newspaper":"Le Patriote","country":"Côte d'Ivoire","type":"articles"}]},{"name":"Mosquée de la Riviéra Golf","lat":5.33757653748572,"lng":-3.9788409923568815,"country":"Côte d'Ivoire","articleCount":2,"articles":[{"id":"48503","title":"L'imam Sékou Sylla (Petite mosquée de la Riviera II) : \"Que Guéï arrête de diaboliser l'islam\"","date":"2000-06-30","newspaper":"Le Patriote","country":"Côte d'Ivoire","type":"articles"},{"id":"48584","title":"Conseil consultatif du COSIM à la grande mosquée de la Riviera : les musulmans déçus de Guéï et du CNSP","date":"2000-08-14","newspaper":"Le Patriote","country":"Côte d'Ivoire","type":"articles"}]},{"name":"Kong","lat":9.150632,"lng":-4.610263,"country":"Côte d'Ivoire","articleCount":2,"articles":[{"id":"48587","title":"Convocation des Imams par le Colonel Déon : la grande colère des musulmans","date":"2000-08-25","newspaper":"Le Patriote","country":"Côte d'Ivoire","type":"articles"},{"id":"73682","title":"Aboubacar Fofana (président du Conseil supérieur des Imams) : \"En Côte d'Ivoire des pasteurs sont marchands d'armes\"","date":"2003-08-27","newspaper":"Le Patriote","country":"Côte d'Ivoire","type":"articles"}]},{"name":"New York","lat":40.712778,"lng":-74.006111,"country":"Benin","articleCount":2,"articles":[{"id":"48630","title":"Rapport accablant sur la Côte d'Ivoire : Human Rights Watch dénonce les violences ethniques et religieuses","date":"2000-12-22","newspaper":"Le Patriote","country":"Côte d'Ivoire","type":"articles"},{"id":"73682","title":"Aboubacar Fofana (président du Conseil supérieur des Imams) : \"En Côte d'Ivoire des pasteurs sont marchands d'armes\"","date":"2003-08-27","newspaper":"Le Patriote","country":"Côte d'Ivoire","type":"articles"}]},{"name":"Gagnoa","lat":6.13333,"lng":-5.93333,"country":"Côte d'Ivoire","articleCount":2,"articles":[{"id":"48669","title":"Réconciliation nationale : Gbagbo et les musulmans face à face enfin!","date":"2001-06-09","newspaper":"Le Patriote","country":"Côte d'Ivoire","type":"articles"},{"id":"74352","title":"Crise post-électorale / Un imam sort de sa réserve : \"Cessons de nous maudire en croyant maudire autrui\"","date":"2011-02-03","newspaper":"Le Jour Plus","country":"Côte d'Ivoire","type":"articles"}]},{"name":"Daoukro","lat":7.057778,"lng":-3.966111,"country":"Côte d'Ivoire","articleCount":2,"articles":[{"id":"48672","title":"Le pouvoir veut-il vraiment la réconciliation? Rencontre Gbagbo-musulmans : ce qui n'a pas été révélé par la presse!","date":"2001-06-14","newspaper":"Le Patriote","country":"Côte d'Ivoire","type":"articles"},{"id":"63782","title":"À l'inauguration hier de la mosquée d'Akouédo : Bédié pour l'unité des musulmans","date":"1994-08-20","newspaper":"Fraternité Matin","country":"Côte d'Ivoire","type":"articles"}]},{"name":"Arabie saoudite","lat":25.0,"lng":45.0,"country":"Saudi Arabia","articleCount":2,"articles":[{"id":"62698","title":"Alassane Drame Ouattara a-t-il un avenir politique en Côte d'Ivoire?","date":"1994-01-28","newspaper":"Le Nouvel Horizon","country":"Côte d'Ivoire","type":"articles"},{"id":"74083","title":"Rentré hier de la Mecque : Mabri veut les élections en février","date":"2009-12-02","newspaper":"Le Jour Plus","country":"Côte d'Ivoire","type":"articles"}]},{"name":"Algérie","lat":28.0,"lng":3.0,"country":"Algeria","articleCount":2,"articles":[{"id":"62698","title":"Alassane Drame Ouattara a-t-il un avenir politique en Côte d'Ivoire?","date":"1994-01-28","newspaper":"Le Nouvel Horizon","country":"Côte d'Ivoire","type":"articles"},{"id":"64680","title":"Changement de régime politique en Côte d'Ivoire : chapelles et mosquées au village","date":"1999-12-30","newspaper":"Fraternité Matin","country":"Côte d'Ivoire","type":"articles"}]},{"name":"Abidjan-Plateau","lat":5.32549,"lng":-4.02014,"country":"Côte d'Ivoire","articleCount":2,"articles":[{"id":"63782","title":"À l'inauguration hier de la mosquée d'Akouédo : Bédié pour l'unité des musulmans","date":"1994-08-20","newspaper":"Fraternité Matin","country":"Côte d'Ivoire","type":"articles"},{"id":"63981","title":"Événements à la mosquée de Banco II (Abobo) : les résultats de la commission d'enquête","date":"1994-08-23","newspaper":"Fraternité Matin","country":"Côte d'Ivoire","type":"articles"}]},{"name":"Daloa","lat":6.866667,"lng":-6.45,"country":"Côte d'Ivoire","articleCount":1,"articles":[{"id":"46399","title":"Forum pour la réconciliation nationale","date":"2001-10-24","newspaper":"Notre Voie","country":"Côte d'Ivoire","type":"articles"}]},{"name":"Russie","lat":66.416667,"lng":94.25,"country":"Russia","articleCount":1,"articles":[{"id":"46447","title":"Agora : Laurent Gbagbo et la laïcité de l'Etat","date":"2003-10-06","newspaper":"Notre Voie","country":"Côte d'Ivoire","type":"articles"}]},{"name":"Stade Félix Houphouët-Boigny","lat":5.32825,"lng":-4.018417,"country":"Côte d'Ivoire","articleCount":1,"articles":[{"id":"46447","title":"Agora : Laurent Gbagbo et la laïcité de l'Etat","date":"2003-10-06","newspaper":"Notre Voie","country":"Côte d'Ivoire","type":"articles"}]},{"name":"Bonoua","lat":5.2666666666667,"lng":-3.6,"country":"Côte d'Ivoire","articleCount":1,"articles":[{"id":"46726","title":"Réconciliation nationale : ceux qui vont faire échouer Banny","date":"2011-09-08","newspaper":"Notre Voie","country":"Côte d'Ivoire","type":"articles"}]},{"name":"Région des Savanes","lat":10.5,"lng":0.5,"country":"Togo","articleCount":1,"articles":[{"id":"48255","title":"Alassane, la charte et les deux imams","date":"2000-06-09","newspaper":"Notre Voie","country":"Côte d'Ivoire","type":"articles"}]},{"name":"Koumassi","lat":5.3,"lng":-3.95,"country":"Côte d'Ivoire","articleCount":1,"articles":[{"id":"48335","title":"Affaire \"Il n'y a pas un nord musulman contre un sud chrétien\" de Soro : or donc la rébellion reposait sur des arguments fallacieux","date":"2017-08-04","newspaper":"Notre Voie","country":"Côte d'Ivoire","type":"articles"}]},{"name":"République démocratique du Congo","lat":0,"lng":0,"country":"Unknown","articleCount":1,"articles":[{"id":"48503","title":"L'imam Sékou Sylla (Petite mosquée de la Riviera II) : \"Que Guéï arrête de diaboliser l'islam\"","date":"2000-06-30","newspaper":"Le Patriote","country":"Côte d'Ivoire","type":"articles"}]},{"name":"Angola","lat":-12.35,"lng":17.35,"country":"Angola","articleCount":1,"articles":[{"id":"48503","title":"L'imam Sékou Sylla (Petite mosquée de la Riviera II) : \"Que Guéï arrête de diaboliser l'islam\"","date":"2000-06-30","newspaper":"Le Patriote","country":"Côte d'Ivoire","type":"articles"}]},{"name":"Riviéra 2","lat":5.347059329725747,"lng":-3.977945412685864,"country":"Côte d'Ivoire","articleCount":1,"articles":[{"id":"48503","title":"L'imam Sékou Sylla (Petite mosquée de la Riviera II) : \"Que Guéï arrête de diaboliser l'islam\"","date":"2000-06-30","newspaper":"Le Patriote","country":"Côte d'Ivoire","type":"articles"}]},{"name":"Palais des Sports de Treichville","lat":5.298056,"lng":-4.005278,"country":"Côte d'Ivoire","articleCount":1,"articles":[{"id":"48584","title":"Conseil consultatif du COSIM à la grande mosquée de la Riviera : les musulmans déçus de Guéï et du CNSP","date":"2000-08-14","newspaper":"Le Patriote","country":"Côte d'Ivoire","type":"articles"}]},{"name":"Anyama","lat":5.4944444444444,"lng":-4.0516666666667,"country":"Côte d'Ivoire","articleCount":1,"articles":[{"id":"48587","title":"Convocation des Imams par le Colonel Déon : la grande colère des musulmans","date":"2000-08-25","newspaper":"Le Patriote","country":"Côte d'Ivoire","type":"articles"}]},{"name":"Grande Mosquée de l'Avenue 8","lat":0,"lng":0,"country":"Unknown","articleCount":1,"articles":[{"id":"48588","title":"Rencontre avec les Imams : Guéi promet la fin du harcèlement contre les musulmans","date":"2000-08-30","newspaper":"Le Patriote","country":"Côte d'Ivoire","type":"articles"}]},{"name":"Treichville","lat":5.3,"lng":-4.0,"country":"Côte d'Ivoire","articleCount":1,"articles":[{"id":"48588","title":"Rencontre avec les Imams : Guéi promet la fin du harcèlement contre les musulmans","date":"2000-08-30","newspaper":"Le Patriote","country":"Côte d'Ivoire","type":"articles"}]},{"name":"Mosquée An Nour Riviera 2","lat":5.351224783601886,"lng":-3.980895863811308,"country":"Côte d'Ivoire","articleCount":1,"articles":[{"id":"48594","title":"Présidentielle 2000 : l'appel du COSIM aux fidèles musulmans","date":"2000-10-21","newspaper":"Le Patriote","country":"Côte d'Ivoire","type":"articles"}]},{"name":"Cocody Angré","lat":5.386217444874156,"lng":-3.9826822579490044,"country":"Côte d'Ivoire","articleCount":1,"articles":[{"id":"48594","title":"Présidentielle 2000 : l'appel du COSIM aux fidèles musulmans","date":"2000-10-21","newspaper":"Le Patriote","country":"Côte d'Ivoire","type":"articles"}]},{"name":"Touba","lat":8.283333,"lng":-7.683333,"country":"Côte d'Ivoire","articleCount":1,"articles":[{"id":"48594","title":"Présidentielle 2000 : l'appel du COSIM aux fidèles musulmans","date":"2000-10-21","newspaper":"Le Patriote","country":"Côte d'Ivoire","type":"articles"}]},{"name":"Bonon","lat":6.9333333333333,"lng":-6.05,"country":"Côte d'Ivoire","articleCount":1,"articles":[{"id":"48594","title":"Présidentielle 2000 : l'appel du COSIM aux fidèles musulmans","date":"2000-10-21","newspaper":"Le Patriote","country":"Côte d'Ivoire","type":"articles"}]},{"name":"San-Pédro","lat":4.733333,"lng":-6.633333,"country":"Burkina Faso","articleCount":1,"articles":[{"id":"48669","title":"Réconciliation nationale : Gbagbo et les musulmans face à face enfin!","date":"2001-06-09","newspaper":"Le Patriote","country":"Côte d'Ivoire","type":"articles"}]},{"name":"Divo","lat":5.837222,"lng":-5.357222,"country":"Côte d'Ivoire","articleCount":1,"articles":[{"id":"48669","title":"Réconciliation nationale : Gbagbo et les musulmans face à face enfin!","date":"2001-06-09","newspaper":"Le Patriote","country":"Côte d'Ivoire","type":"articles"}]},{"name":"Lakota","lat":5.8475,"lng":-5.681944,"country":"Côte d'Ivoire","articleCount":1,"articles":[{"id":"48672","title":"Le pouvoir veut-il vraiment la réconciliation? Rencontre Gbagbo-musulmans : ce qui n'a pas été révélé par la presse!","date":"2001-06-14","newspaper":"Le Patriote","country":"Côte d'Ivoire","type":"articles"}]},{"name":"Rwanda","lat":-2.0,"lng":30.0,"country":"Rwanda","articleCount":1,"articles":[{"id":"48699","title":"M. Benoît Scheuer (Réalisateur du film Côte d'Ivoire, poudrière identitaire) persiste et signe : \"Il y a des tentations génocidaires en Côte d'Ivoire\"","date":"2001-07-19","newspaper":"Le Patriote","country":"Côte d'Ivoire","type":"articles"}]},{"name":"Allemagne","lat":51.5,"lng":10.5,"country":"Germany","articleCount":1,"articles":[{"id":"48699","title":"M. Benoît Scheuer (Réalisateur du film Côte d'Ivoire, poudrière identitaire) persiste et signe : \"Il y a des tentations génocidaires en Côte d'Ivoire\"","date":"2001-07-19","newspaper":"Le Patriote","country":"Côte d'Ivoire","type":"articles"}]},{"name":"Grande mosquée des II-Plateaux Aghien","lat":5.382535557731071,"lng":-3.993870062858185,"country":"Côte d'Ivoire","articleCount":1,"articles":[{"id":"48717","title":"Résolution de la crise socio-politique en Côte d'Ivoire : le CNI demande l'implication de la France","date":"2001-12-04","newspaper":"Le Patriote","country":"Côte d'Ivoire","type":"articles"}]},{"name":"Marseille","lat":43.296666666667,"lng":5.3763888888889,"country":"France","articleCount":1,"articles":[{"id":"62698","title":"Alassane Drame Ouattara a-t-il un avenir politique en Côte d'Ivoire?","date":"1994-01-28","newspaper":"Le Nouvel Horizon","country":"Côte d'Ivoire","type":"articles"}]},{"name":"Tengréla","lat":10.481111111111,"lng":-6.4069444444444,"country":"Côte d'Ivoire","articleCount":1,"articles":[{"id":"62698","title":"Alassane Drame Ouattara a-t-il un avenir politique en Côte d'Ivoire?","date":"1994-01-28","newspaper":"Le Nouvel Horizon","country":"Côte d'Ivoire","type":"articles"}]},{"name":"Dakar","lat":14.731944444444,"lng":-17.457222222222,"country":"Senegal","articleCount":1,"articles":[{"id":"62698","title":"Alassane Drame Ouattara a-t-il un avenir politique en Côte d'Ivoire?","date":"1994-01-28","newspaper":"Le Nouvel Horizon","country":"Côte d'Ivoire","type":"articles"}]},{"name":"Hôtel Ivoire","lat":5.3269,"lng":-4.00547,"country":"Côte d'Ivoire","articleCount":1,"articles":[{"id":"62698","title":"Alassane Drame Ouattara a-t-il un avenir politique en Côte d'Ivoire?","date":"1994-01-28","newspaper":"Le Nouvel Horizon","country":"Côte d'Ivoire","type":"articles"}]},{"name":"Bocanda","lat":7.0666666666667,"lng":-4.5,"country":"Côte d'Ivoire","articleCount":1,"articles":[{"id":"63782","title":"À l'inauguration hier de la mosquée d'Akouédo : Bédié pour l'unité des musulmans","date":"1994-08-20","newspaper":"Fraternité Matin","country":"Côte d'Ivoire","type":"articles"}]},{"name":"Abobo Banco","lat":5.41301,"lng":-4.02092,"country":"Côte d'Ivoire","articleCount":1,"articles":[{"id":"63981","title":"Événements à la mosquée de Banco II (Abobo) : les résultats de la commission d'enquête","date":"1994-08-23","newspaper":"Fraternité Matin","country":"Côte d'Ivoire","type":"articles"}]},{"name":"Mankono","lat":8.05,"lng":-6.18333333,"country":"Côte d'Ivoire","articleCount":1,"articles":[{"id":"73682","title":"Aboubacar Fofana (président du Conseil supérieur des Imams) : \"En Côte d'Ivoire des pasteurs sont marchands d'armes\"","date":"2003-08-27","newspaper":"Le Patriote","country":"Côte d'Ivoire","type":"articles"}]},{"name":"Boundiali","lat":9.516667,"lng":-6.483333,"country":"Côte d'Ivoire","articleCount":1,"articles":[{"id":"73682","title":"Aboubacar Fofana (président du Conseil supérieur des Imams) : \"En Côte d'Ivoire des pasteurs sont marchands d'armes\"","date":"2003-08-27","newspaper":"Le Patriote","country":"Côte d'Ivoire","type":"articles"}]},{"name":"Nigéria","lat":10.0,"lng":8.0,"country":"Nigeria","articleCount":1,"articles":[{"id":"73682","title":"Aboubacar Fofana (président du Conseil supérieur des Imams) : \"En Côte d'Ivoire des pasteurs sont marchands d'armes\"","date":"2003-08-27","newspaper":"Le Patriote","country":"Côte d'Ivoire","type":"articles"}]},{"name":"Aéroport International Félix Houphouët-Boigny","lat":5.261417,"lng":-3.925778,"country":"Côte d'Ivoire","articleCount":1,"articles":[{"id":"74083","title":"Rentré hier de la Mecque : Mabri veut les élections en février","date":"2009-12-02","newspaper":"Le Jour Plus","country":"Côte d'Ivoire","type":"articles"}]},{"name":"Angleterre","lat":53.0,"lng":-1.0,"country":"United Kingdom","articleCount":1,"articles":[{"id":"74352","title":"Crise post-électorale / Un imam sort de sa réserve : \"Cessons de nous maudire en croyant maudire autrui\"","date":"2011-02-03","newspaper":"Le Jour Plus","country":"Côte d'Ivoire","type":"articles"}]},{"name":"Canada","lat":60.10867,"lng":-113.64258,"country":"Canada","articleCount":1,"articles":[{"id":"74352","title":"Crise post-électorale / Un imam sort de sa réserve : \"Cessons de nous maudire en croyant maudire autrui\"","date":"2011-02-03","newspaper":"Le Jour Plus","country":"Côte d'Ivoire","type":"articles"}]},{"name":"Suisse","lat":47.00016,"lng":8.01427,"country":"Switzerland","articleCount":1,"articles":[{"id":"74352","title":"Crise post-électorale / Un imam sort de sa réserve : \"Cessons de nous maudire en croyant maudire autrui\"","date":"2011-02-03","newspaper":"Le Jour Plus","country":"Côte d'Ivoire","type":"articles"}]},{"name":"Lomé","lat":6.12874,"lng":1.22154,"country":"Togo","articleCount":1,"articles":[{"id":"74352","title":"Crise post-électorale / Un imam sort de sa réserve : \"Cessons de nous maudire en croyant maudire autrui\"","date":"2011-02-03","newspaper":"Le Jour Plus","country":"Côte d'Ivoire","type":"articles"}]},{"name":"Ouagadougou","lat":12.36566,"lng":-1.53388,"country":"Burkina Faso","articleCount":1,"articles":[{"id":"74352","title":"Crise post-électorale / Un imam sort de sa réserve : \"Cessons de nous maudire en croyant maudire autrui\"","date":"2011-02-03","newspaper":"Le Jour Plus","country":"Côte d'Ivoire","type":"articles"}]},{"name":"Accra","lat":5.533333,"lng":-0.216667,"country":"Benin","articleCount":1,"articles":[{"id":"74352","title":"Crise post-électorale / Un imam sort de sa réserve : \"Cessons de nous maudire en croyant maudire autrui\"","date":"2011-02-03","newspaper":"Le Jour Plus","country":"Côte d'Ivoire","type":"articles"}]},{"name":"Abengourou","lat":6.729722,"lng":-3.496389,"country":"Côte d'Ivoire","articleCount":1,"articles":[{"id":"74352","title":"Crise post-électorale / Un imam sort de sa réserve : \"Cessons de nous maudire en croyant maudire autrui\"","date":"2011-02-03","newspaper":"Le Jour Plus","country":"Côte d'Ivoire","type":"articles"}]},{"name":"Duékoué","lat":6.741944,"lng":-7.349167,"country":"Côte d'Ivoire","articleCount":1,"articles":[{"id":"74352","title":"Crise post-électorale / Un imam sort de sa réserve : \"Cessons de nous maudire en croyant maudire autrui\"","date":"2011-02-03","newspaper":"Le Jour Plus","country":"Côte d'Ivoire","type":"articles"}]}]}