{"id":953,"name":"Achille Tapsoba","type":"Personnes","stats":{"articleCount":3,"countries":["Burkina Faso"],"dateRange":{"first":"2012-08-07","last":"2013-09-23"}},"locations":[{"name":"Burkina Faso","lat":12.5,"lng":-1.66667,"country":"Burkina Faso","articleCount":2,"articles":[{"id":"2773","title":"Le Sénat : instrument du diable pour les religions","date":"2013-09-23","newspaper":"L'Observateur Paalga","country":"Burkina Faso","type":"articles"},{"id":"5823","title":"Les catholiques rejettent, les musulmans bénissent et les protestants…","date":"2013-09-15","newspaper":"L'Observateur Paalga","country":"Burkina Faso","type":"articles"}]},{"name":"Palais Kosyam","lat":12.288426,"lng":-1.50273,"country":"Burkina Faso","articleCount":1,"articles":[{"id":"2773","title":"Le Sénat : instrument du diable pour les religions","date":"2013-09-23","newspaper":"L'Observateur Paalga","country":"Burkina Faso","type":"articles"}]},{"name":"Ouagadougou","lat":12.36566,"lng":-1.53388,"country":"Burkina Faso","articleCount":1,"articles":[{"id":"3353","title":"Arrondissement n°2 (nouveau) de Ouagadougou : des vivres aux fidèles musulmans","date":"2012-08-07","newspaper":"Sidwaya","country":"Burkina Faso","type":"articles"}]},{"name":"Bobo-Dioulasso","lat":11.17715,"lng":-4.2979,"country":"Burkina Faso","articleCount":1,"articles":[{"id":"5823","title":"Les catholiques rejettent, les musulmans bénissent et les protestants…","date":"2013-09-15","newspaper":"L'Observateur Paalga","country":"Burkina Faso","type":"articles"}]}]}