{"term":"terrorisme","total_occurrences":155647,"articles_with_term":1015,"unique_words":10647,"max_word_count":1427,"words":[{"word":"pays","count":1427},{"word":"islam","count":1141},{"word":"attaque","count":1138},{"word":"burkina","count":985},{"word":"dire","count":975},{"word":"musulman","count":966},{"word":"groupe","count":960},{"word":"etat","count":936},{"word":"lutte","count":894},{"word":"force","count":847},{"word":"sécurité","count":814},{"word":"entrer","count":716},{"word":"paix","count":703},{"word":"président","count":660},{"word":"faso","count":656},{"word":"population","count":644},{"word":"sahel","count":606},{"word":"religion","count":591},{"word":"chef","count":552},{"word":"acte","count":542},{"word":"communauté","count":520},{"word":"national","count":488},{"word":"armée","count":487},{"word":"islamique","count":476},{"word":"religieux","count":469},{"word":"militaire","count":466},{"word":"région","count":453},{"word":"burkinabè","count":442},{"word":"monde","count":440},{"word":"défense","count":438},{"word":"situation","count":417},{"word":"personne","count":412},{"word":"face","count":406},{"word":"menace","count":403},{"word":"action","count":400},{"word":"ministre","count":390},{"word":"sécuritaire","count":385},{"word":"politique","count":383},{"word":"niger","count":375},{"word":"celer","count":365},{"word":"luire","count":362},{"word":"sou","count":348},{"word":"guerre","count":347},{"word":"international","count":345},{"word":"zone","count":342},{"word":"question","count":326},{"word":"également","count":324},{"word":"permettre","count":320},{"word":"social","count":316},{"word":"homme","count":311},{"word":"gouvernement","count":307},{"word":"état","count":305},{"word":"mali","count":293},{"word":"violence","count":287},{"word":"afin","count":285},{"word":"général","count":282},{"word":"développement","count":280},{"word":"organisation","count":278},{"word":"ensemble","count":270},{"word":"victime","count":264},{"word":"dieu","count":264},{"word":"vie","count":262},{"word":"afrique","count":257},{"word":"vivre","count":255},{"word":"autorité","count":254},{"word":"peuple","count":254},{"word":"jeune","count":244},{"word":"forme","count":244},{"word":"non","count":243},{"word":"imam","count":242},{"word":"opération","count":238},{"word":"travers","count":238},{"word":"agir","count":237},{"word":"nord","count":235},{"word":"frontière","count":235},{"word":"arme","count":232},{"word":"différent","count":232},{"word":"connaître","count":229},{"word":"mener","count":227},{"word":"prière","count":221},{"word":"violent","count":218},{"word":"ouagadougou","count":215},{"word":"ailleurs","count":214},{"word":"tuer","count":212},{"word":"lutter","count":212},{"word":"civil","count":208},{"word":"phénomène","count":208},{"word":"nom","count":204},{"word":"attentat","count":204},{"word":"mort","count":203},{"word":"cause","count":203},{"word":"surtout","count":201},{"word":"appeler","count":201},{"word":"côte","count":199},{"word":"notamment","count":198},{"word":"bénin","count":198},{"word":"soutien","count":196},{"word":"passer","count":194},{"word":"membre","count":194},{"word":"cadre","count":194}]}