{"id":638,"name":"Centre Culturel Islamique du Burkina","type":"Organisations","stats":{"articleCount":3,"countries":["Burkina Faso","United States of America"],"dateRange":{"first":"2018-04-14","last":"2018-12-07"}},"locations":[{"name":"Ouagadougou","lat":12.36566,"lng":-1.53388,"country":"Burkina Faso","articleCount":2,"articles":[{"id":"3853","title":"Centre islamique : coup de pinceaux du diplomate américain","date":"2018-06-09","newspaper":"Burkina 24","country":"Burkina Faso","type":"articles"},{"id":"3854","title":"Vivre-ensemble au Burkina : menaces et défis, selon l'Imam Alidou Ilboudo","date":"2018-04-14","newspaper":"Burkina 24","country":"Burkina Faso","type":"articles"}]},{"name":"Burkina Faso","lat":12.5,"lng":-1.66667,"country":"Burkina Faso","articleCount":1,"articles":[{"id":"2231","title":"Centre culturel islamique du Burkina (CCIB) : un panel pour parler du vivre-ensemble","date":"2018-12-07","newspaper":"Le Pays","country":"Burkina Faso","type":"articles"}]},{"name":"États-Unis","lat":39.76,"lng":-98.5,"country":"United States of America","articleCount":1,"articles":[{"id":"3853","title":"Centre islamique : coup de pinceaux du diplomate américain","date":"2018-06-09","newspaper":"Burkina 24","country":"Burkina Faso","type":"articles"}]}]}