{"id":726,"name":"STMB Tours","type":"Organisations","stats":{"articleCount":41,"countries":["Benin","Burkina Faso","Central African Rep.","Côte d'Ivoire","France","Gambia","Ghana","Kuwait","Mali","Niger","Nigeria","Pakistan","Saudi Arabia","Senegal","Sudan"],"dateRange":{"first":"2007-11-12","last":"2012-10-01"}},"locations":[{"name":"Ouagadougou","lat":12.36566,"lng":-1.53388,"country":"Burkina Faso","articleCount":34,"articles":[{"id":"2256","title":"Organisation du Hadj 2011 : pour une concurrence au niveau du transport aérien","date":"2011-09-14","newspaper":"Le Pays","country":"Burkina Faso","type":"articles"},{"id":"2285","title":"Des pèlerins interpellent le MATD sur leurs déboires","date":"2010-01-24","newspaper":"Le Pays","country":"Burkina Faso","type":"articles"},{"id":"2356","title":"Hadj 2011 : 2 915 pèlerins pour l'édition","date":"2011-10-23","newspaper":"Le Pays","country":"Burkina Faso","type":"articles"},{"id":"2359","title":"Organisation du Hadj 2008 : sept agences retenues","date":"2008-07-08","newspaper":"Le Pays","country":"Burkina Faso","type":"articles"},{"id":"2365","title":"Hadj 2007 : les organisateurs contre le retour de l'État dans l'organisation","date":"2008-02-04","newspaper":"Le Pays","country":"Burkina Faso","type":"articles"},{"id":"2426","title":"Le choix de STMB-Tours fait débat","date":"2010-10-06","newspaper":"Le Pays","country":"Burkina Faso","type":"articles"},{"id":"2442","title":"Hadj 2007 : 2000 visas pour les Burkinabè","date":"2007-11-12","newspaper":"Le Pays","country":"Burkina Faso","type":"articles"},{"id":"2552","title":"518 pèlerins burkinabè pour le premier vol","date":"2010-11-03","newspaper":"Le Pays","country":"Burkina Faso","type":"articles"},{"id":"2599","title":"Hadj : des propositions pour une gestion saine et efficace","date":"2008-01-29","newspaper":"Le Pays","country":"Burkina Faso","type":"articles"},{"id":"2619","title":"Les premiers pèlerins ont décollé","date":"2009-11-08","newspaper":"Le Pays","country":"Burkina Faso","type":"articles"},{"id":"2720","title":"Hadj 2011 : 1er vol ce soir à 23h30","date":"2011-10-18","newspaper":"L'Observateur Paalga","country":"Burkina Faso","type":"articles"},{"id":"2725","title":"Hadj 2008 : premier test d'une « privatisation encadrée »","date":"2008-11-13","newspaper":"L'Observateur Paalga","country":"Burkina Faso","type":"articles"},{"id":"2743","title":"Hadj 2008 : le point des préparatifs","date":"2008-10-09","newspaper":"L'Observateur Paalga","country":"Burkina Faso","type":"articles"},{"id":"2788","title":"Hadj 2011 : triste sort pour 144 pèlerins recalés","date":"2011-10-25","newspaper":"L'Observateur Paalga","country":"Burkina Faso","type":"articles"},{"id":"2802","title":"Retour des pèlerins burkinabè : \"On m'a volé mon fauteuil roulant à la Mecque\"","date":"2008-12-16","newspaper":"L'Observateur Paalga","country":"Burkina Faso","type":"articles"},{"id":"2888","title":"Propositions pour une prise en charge","date":"2007-12-04","newspaper":"L'Observateur Paalga","country":"Burkina Faso","type":"articles"},{"id":"2943","title":"Les premiers pèlerins de retour au bercail","date":"2010-12-13","newspaper":"Sidwaya","country":"Burkina Faso","type":"articles"},{"id":"2946","title":"Hadj 2009 : une seule agence agréée pour l'organisation du pèlerinage","date":"2009-06-01","newspaper":"Sidwaya","country":"Burkina Faso","type":"articles"},{"id":"2974","title":"Déjà des remous dans le volet organisationnel","date":"2010-09-20","newspaper":"Sidwaya","country":"Burkina Faso","type":"articles"},{"id":"3010","title":"Pèlerinage 2009 : les péripéties d'un départ pour les lieux saints","date":"2009-11-11","newspaper":"Sidwaya","country":"Burkina Faso","type":"articles"},{"id":"3041","title":"Hadj 2007 : la première vague des pèlerins de retour à Sya","date":"2008-01-15","newspaper":"Sidwaya","country":"Burkina Faso","type":"articles"},{"id":"3061","title":"Hadj édition 2010 : 1 million 193 mille F CFA pour le billet d'avion","date":"2010-09-14","newspaper":"Sidwaya","country":"Burkina Faso","type":"articles"},{"id":"3107","title":"518 pèlerins ouvrent le vol vers les lieux saints","date":"2010-11-04","newspaper":"Sidwaya","country":"Burkina Faso","type":"articles"},{"id":"3111","title":"Hadj 2009 : les premiers pèlerins sont partis","date":"2009-11-09","newspaper":"Sidwaya","country":"Burkina Faso","type":"articles"},{"id":"3114","title":"Les premiers El Hadj et Hadja de retour au bercail","date":"2008-12-16","newspaper":"Sidwaya","country":"Burkina Faso","type":"articles"},{"id":"3115","title":"Hadj 2008 : 274 candidats ouvrent le vol","date":"2008-11-11","newspaper":"Sidwaya","country":"Burkina Faso","type":"articles"},{"id":"3149","title":"Hadj 2008 : c'est le privé qui gagne !","date":"2008-12-18","newspaper":"Sidwaya","country":"Burkina Faso","type":"articles"},{"id":"3195","title":"Hadj 2011 : départ des pèlerins aujourd'hui","date":"2011-10-18","newspaper":"Sidwaya","country":"Burkina Faso","type":"articles"},{"id":"23281","title":"Hadj 2009 : déjà un millier de pèlerins inscrits","date":"2009-10-21","newspaper":"FasoZine","country":"Burkina Faso","type":"articles"},{"id":"23282","title":"Hadj 2009 : les premiers pèlerins burkinabè sont partis","date":"2009-11-08","newspaper":"FasoZine","country":"Burkina Faso","type":"articles"},{"id":"23284","title":"Hadj 2009 : STMB Tour dénonce un recrutement clandestin de pèlerins","date":"2009-11-26","newspaper":"FasoZine","country":"Burkina Faso","type":"articles"},{"id":"23329","title":"Pèlerinage à la Mecque : des musulmans dénoncent la cherté du billet d'avion","date":"2011-09-18","newspaper":"FasoZine","country":"Burkina Faso","type":"articles"},{"id":"23344","title":"Hadj 2011 : «On ne peut pas donner un tel marché à un seul transporteur aérien»","date":"2011-11-01","newspaper":"FasoZine","country":"Burkina Faso","type":"articles"},{"id":"12075","title":"Le CERFIste #13","date":"2010-12","newspaper":"Le CERFIste","country":"Burkina Faso","type":"publications"}]},{"name":"La Mecque","lat":21.4225,"lng":39.826111,"country":"Saudi Arabia","articleCount":25,"articles":[{"id":"2285","title":"Des pèlerins interpellent le MATD sur leurs déboires","date":"2010-01-24","newspaper":"Le Pays","country":"Burkina Faso","type":"articles"},{"id":"2356","title":"Hadj 2011 : 2 915 pèlerins pour l'édition","date":"2011-10-23","newspaper":"Le Pays","country":"Burkina Faso","type":"articles"},{"id":"2359","title":"Organisation du Hadj 2008 : sept agences retenues","date":"2008-07-08","newspaper":"Le Pays","country":"Burkina Faso","type":"articles"},{"id":"2365","title":"Hadj 2007 : les organisateurs contre le retour de l'État dans l'organisation","date":"2008-02-04","newspaper":"Le Pays","country":"Burkina Faso","type":"articles"},{"id":"2426","title":"Le choix de STMB-Tours fait débat","date":"2010-10-06","newspaper":"Le Pays","country":"Burkina Faso","type":"articles"},{"id":"2442","title":"Hadj 2007 : 2000 visas pour les Burkinabè","date":"2007-11-12","newspaper":"Le Pays","country":"Burkina Faso","type":"articles"},{"id":"2599","title":"Hadj : des propositions pour une gestion saine et efficace","date":"2008-01-29","newspaper":"Le Pays","country":"Burkina Faso","type":"articles"},{"id":"2619","title":"Les premiers pèlerins ont décollé","date":"2009-11-08","newspaper":"Le Pays","country":"Burkina Faso","type":"articles"},{"id":"2725","title":"Hadj 2008 : premier test d'une « privatisation encadrée »","date":"2008-11-13","newspaper":"L'Observateur Paalga","country":"Burkina Faso","type":"articles"},{"id":"2743","title":"Hadj 2008 : le point des préparatifs","date":"2008-10-09","newspaper":"L'Observateur Paalga","country":"Burkina Faso","type":"articles"},{"id":"2802","title":"Retour des pèlerins burkinabè : \"On m'a volé mon fauteuil roulant à la Mecque\"","date":"2008-12-16","newspaper":"L'Observateur Paalga","country":"Burkina Faso","type":"articles"},{"id":"2943","title":"Les premiers pèlerins de retour au bercail","date":"2010-12-13","newspaper":"Sidwaya","country":"Burkina Faso","type":"articles"},{"id":"2946","title":"Hadj 2009 : une seule agence agréée pour l'organisation du pèlerinage","date":"2009-06-01","newspaper":"Sidwaya","country":"Burkina Faso","type":"articles"},{"id":"2949","title":"Hadj 2008 : 2 114 pèlerins burkinabè en terre sainte","date":"2008-12-05","newspaper":"Sidwaya","country":"Burkina Faso","type":"articles"},{"id":"2974","title":"Déjà des remous dans le volet organisationnel","date":"2010-09-20","newspaper":"Sidwaya","country":"Burkina Faso","type":"articles"},{"id":"3010","title":"Pèlerinage 2009 : les péripéties d'un départ pour les lieux saints","date":"2009-11-11","newspaper":"Sidwaya","country":"Burkina Faso","type":"articles"},{"id":"3012","title":"Louis Yaméogo, coordonnateur de l'Oavp : \"Nos premiers pèlerins décollent aujourd'hui\"","date":"2008-11-12","newspaper":"Sidwaya","country":"Burkina Faso","type":"articles"},{"id":"3036","title":"Les insuffisances du Hadj 2009 expliquées aux députés","date":"2010-03-29","newspaper":"Sidwaya","country":"Burkina Faso","type":"articles"},{"id":"3041","title":"Hadj 2007 : la première vague des pèlerins de retour à Sya","date":"2008-01-15","newspaper":"Sidwaya","country":"Burkina Faso","type":"articles"},{"id":"3061","title":"Hadj édition 2010 : 1 million 193 mille F CFA pour le billet d'avion","date":"2010-09-14","newspaper":"Sidwaya","country":"Burkina Faso","type":"articles"},{"id":"3111","title":"Hadj 2009 : les premiers pèlerins sont partis","date":"2009-11-09","newspaper":"Sidwaya","country":"Burkina Faso","type":"articles"},{"id":"3114","title":"Les premiers El Hadj et Hadja de retour au bercail","date":"2008-12-16","newspaper":"Sidwaya","country":"Burkina Faso","type":"articles"},{"id":"3149","title":"Hadj 2008 : c'est le privé qui gagne !","date":"2008-12-18","newspaper":"Sidwaya","country":"Burkina Faso","type":"articles"},{"id":"3195","title":"Hadj 2011 : départ des pèlerins aujourd'hui","date":"2011-10-18","newspaper":"Sidwaya","country":"Burkina Faso","type":"articles"},{"id":"3314","title":"Hadj 2011 : les acteurs se rejettent la responsabilité de la mauvaise organisation","date":"2012-01-03","newspaper":"Sidwaya","country":"Burkina Faso","type":"articles"}]},{"name":"Arabie saoudite","lat":25.0,"lng":45.0,"country":"Saudi Arabia","articleCount":23,"articles":[{"id":"2285","title":"Des pèlerins interpellent le MATD sur leurs déboires","date":"2010-01-24","newspaper":"Le Pays","country":"Burkina Faso","type":"articles"},{"id":"2359","title":"Organisation du Hadj 2008 : sept agences retenues","date":"2008-07-08","newspaper":"Le Pays","country":"Burkina Faso","type":"articles"},{"id":"2365","title":"Hadj 2007 : les organisateurs contre le retour de l'État dans l'organisation","date":"2008-02-04","newspaper":"Le Pays","country":"Burkina Faso","type":"articles"},{"id":"2442","title":"Hadj 2007 : 2000 visas pour les Burkinabè","date":"2007-11-12","newspaper":"Le Pays","country":"Burkina Faso","type":"articles"},{"id":"2552","title":"518 pèlerins burkinabè pour le premier vol","date":"2010-11-03","newspaper":"Le Pays","country":"Burkina Faso","type":"articles"},{"id":"2599","title":"Hadj : des propositions pour une gestion saine et efficace","date":"2008-01-29","newspaper":"Le Pays","country":"Burkina Faso","type":"articles"},{"id":"2619","title":"Les premiers pèlerins ont décollé","date":"2009-11-08","newspaper":"Le Pays","country":"Burkina Faso","type":"articles"},{"id":"2720","title":"Hadj 2011 : 1er vol ce soir à 23h30","date":"2011-10-18","newspaper":"L'Observateur Paalga","country":"Burkina Faso","type":"articles"},{"id":"2725","title":"Hadj 2008 : premier test d'une « privatisation encadrée »","date":"2008-11-13","newspaper":"L'Observateur Paalga","country":"Burkina Faso","type":"articles"},{"id":"2743","title":"Hadj 2008 : le point des préparatifs","date":"2008-10-09","newspaper":"L'Observateur Paalga","country":"Burkina Faso","type":"articles"},{"id":"2788","title":"Hadj 2011 : triste sort pour 144 pèlerins recalés","date":"2011-10-25","newspaper":"L'Observateur Paalga","country":"Burkina Faso","type":"articles"},{"id":"2790","title":"Hadj 2010 : le pèlerin exempté des taxes aéronautiques","date":"2010-09-15","newspaper":"L'Observateur Paalga","country":"Burkina Faso","type":"articles"},{"id":"2943","title":"Les premiers pèlerins de retour au bercail","date":"2010-12-13","newspaper":"Sidwaya","country":"Burkina Faso","type":"articles"},{"id":"2946","title":"Hadj 2009 : une seule agence agréée pour l'organisation du pèlerinage","date":"2009-06-01","newspaper":"Sidwaya","country":"Burkina Faso","type":"articles"},{"id":"2949","title":"Hadj 2008 : 2 114 pèlerins burkinabè en terre sainte","date":"2008-12-05","newspaper":"Sidwaya","country":"Burkina Faso","type":"articles"},{"id":"3012","title":"Louis Yaméogo, coordonnateur de l'Oavp : \"Nos premiers pèlerins décollent aujourd'hui\"","date":"2008-11-12","newspaper":"Sidwaya","country":"Burkina Faso","type":"articles"},{"id":"3041","title":"Hadj 2007 : la première vague des pèlerins de retour à Sya","date":"2008-01-15","newspaper":"Sidwaya","country":"Burkina Faso","type":"articles"},{"id":"3107","title":"518 pèlerins ouvrent le vol vers les lieux saints","date":"2010-11-04","newspaper":"Sidwaya","country":"Burkina Faso","type":"articles"},{"id":"3111","title":"Hadj 2009 : les premiers pèlerins sont partis","date":"2009-11-09","newspaper":"Sidwaya","country":"Burkina Faso","type":"articles"},{"id":"3195","title":"Hadj 2011 : départ des pèlerins aujourd'hui","date":"2011-10-18","newspaper":"Sidwaya","country":"Burkina Faso","type":"articles"},{"id":"3314","title":"Hadj 2011 : les acteurs se rejettent la responsabilité de la mauvaise organisation","date":"2012-01-03","newspaper":"Sidwaya","country":"Burkina Faso","type":"articles"},{"id":"4545","title":"Organisation du Hadj : on n'est pas totalement sorti de l'auberge","date":"2010-09-20","newspaper":"San Finna","country":"Burkina Faso","type":"articles"},{"id":"8573","title":"Pèlerinage à la Mecque : sur les traces d'un hadj meilleur","date":"2012-10-01","newspaper":"Mutations","country":"Burkina Faso","type":"articles"}]},{"name":"Burkina Faso","lat":12.5,"lng":-1.66667,"country":"Burkina Faso","articleCount":20,"articles":[{"id":"2256","title":"Organisation du Hadj 2011 : pour une concurrence au niveau du transport aérien","date":"2011-09-14","newspaper":"Le Pays","country":"Burkina Faso","type":"articles"},{"id":"2285","title":"Des pèlerins interpellent le MATD sur leurs déboires","date":"2010-01-24","newspaper":"Le Pays","country":"Burkina Faso","type":"articles"},{"id":"2356","title":"Hadj 2011 : 2 915 pèlerins pour l'édition","date":"2011-10-23","newspaper":"Le Pays","country":"Burkina Faso","type":"articles"},{"id":"2359","title":"Organisation du Hadj 2008 : sept agences retenues","date":"2008-07-08","newspaper":"Le Pays","country":"Burkina Faso","type":"articles"},{"id":"2365","title":"Hadj 2007 : les organisateurs contre le retour de l'État dans l'organisation","date":"2008-02-04","newspaper":"Le Pays","country":"Burkina Faso","type":"articles"},{"id":"2442","title":"Hadj 2007 : 2000 visas pour les Burkinabè","date":"2007-11-12","newspaper":"Le Pays","country":"Burkina Faso","type":"articles"},{"id":"2599","title":"Hadj : des propositions pour une gestion saine et efficace","date":"2008-01-29","newspaper":"Le Pays","country":"Burkina Faso","type":"articles"},{"id":"2720","title":"Hadj 2011 : 1er vol ce soir à 23h30","date":"2011-10-18","newspaper":"L'Observateur Paalga","country":"Burkina Faso","type":"articles"},{"id":"2743","title":"Hadj 2008 : le point des préparatifs","date":"2008-10-09","newspaper":"L'Observateur Paalga","country":"Burkina Faso","type":"articles"},{"id":"2788","title":"Hadj 2011 : triste sort pour 144 pèlerins recalés","date":"2011-10-25","newspaper":"L'Observateur Paalga","country":"Burkina Faso","type":"articles"},{"id":"2943","title":"Les premiers pèlerins de retour au bercail","date":"2010-12-13","newspaper":"Sidwaya","country":"Burkina Faso","type":"articles"},{"id":"2946","title":"Hadj 2009 : une seule agence agréée pour l'organisation du pèlerinage","date":"2009-06-01","newspaper":"Sidwaya","country":"Burkina Faso","type":"articles"},{"id":"2949","title":"Hadj 2008 : 2 114 pèlerins burkinabè en terre sainte","date":"2008-12-05","newspaper":"Sidwaya","country":"Burkina Faso","type":"articles"},{"id":"3010","title":"Pèlerinage 2009 : les péripéties d'un départ pour les lieux saints","date":"2009-11-11","newspaper":"Sidwaya","country":"Burkina Faso","type":"articles"},{"id":"3036","title":"Les insuffisances du Hadj 2009 expliquées aux députés","date":"2010-03-29","newspaper":"Sidwaya","country":"Burkina Faso","type":"articles"},{"id":"3061","title":"Hadj édition 2010 : 1 million 193 mille F CFA pour le billet d'avion","date":"2010-09-14","newspaper":"Sidwaya","country":"Burkina Faso","type":"articles"},{"id":"3107","title":"518 pèlerins ouvrent le vol vers les lieux saints","date":"2010-11-04","newspaper":"Sidwaya","country":"Burkina Faso","type":"articles"},{"id":"3114","title":"Les premiers El Hadj et Hadja de retour au bercail","date":"2008-12-16","newspaper":"Sidwaya","country":"Burkina Faso","type":"articles"},{"id":"3195","title":"Hadj 2011 : départ des pèlerins aujourd'hui","date":"2011-10-18","newspaper":"Sidwaya","country":"Burkina Faso","type":"articles"},{"id":"3314","title":"Hadj 2011 : les acteurs se rejettent la responsabilité de la mauvaise organisation","date":"2012-01-03","newspaper":"Sidwaya","country":"Burkina Faso","type":"articles"}]},{"name":"Bobo-Dioulasso","lat":11.17715,"lng":-4.2979,"country":"Burkina Faso","articleCount":15,"articles":[{"id":"2356","title":"Hadj 2011 : 2 915 pèlerins pour l'édition","date":"2011-10-23","newspaper":"Le Pays","country":"Burkina Faso","type":"articles"},{"id":"2442","title":"Hadj 2007 : 2000 visas pour les Burkinabè","date":"2007-11-12","newspaper":"Le Pays","country":"Burkina Faso","type":"articles"},{"id":"2552","title":"518 pèlerins burkinabè pour le premier vol","date":"2010-11-03","newspaper":"Le Pays","country":"Burkina Faso","type":"articles"},{"id":"2599","title":"Hadj : des propositions pour une gestion saine et efficace","date":"2008-01-29","newspaper":"Le Pays","country":"Burkina Faso","type":"articles"},{"id":"2619","title":"Les premiers pèlerins ont décollé","date":"2009-11-08","newspaper":"Le Pays","country":"Burkina Faso","type":"articles"},{"id":"2725","title":"Hadj 2008 : premier test d'une « privatisation encadrée »","date":"2008-11-13","newspaper":"L'Observateur Paalga","country":"Burkina Faso","type":"articles"},{"id":"2743","title":"Hadj 2008 : le point des préparatifs","date":"2008-10-09","newspaper":"L'Observateur Paalga","country":"Burkina Faso","type":"articles"},{"id":"2888","title":"Propositions pour une prise en charge","date":"2007-12-04","newspaper":"L'Observateur Paalga","country":"Burkina Faso","type":"articles"},{"id":"3010","title":"Pèlerinage 2009 : les péripéties d'un départ pour les lieux saints","date":"2009-11-11","newspaper":"Sidwaya","country":"Burkina Faso","type":"articles"},{"id":"3012","title":"Louis Yaméogo, coordonnateur de l'Oavp : \"Nos premiers pèlerins décollent aujourd'hui\"","date":"2008-11-12","newspaper":"Sidwaya","country":"Burkina Faso","type":"articles"},{"id":"3041","title":"Hadj 2007 : la première vague des pèlerins de retour à Sya","date":"2008-01-15","newspaper":"Sidwaya","country":"Burkina Faso","type":"articles"},{"id":"3107","title":"518 pèlerins ouvrent le vol vers les lieux saints","date":"2010-11-04","newspaper":"Sidwaya","country":"Burkina Faso","type":"articles"},{"id":"3111","title":"Hadj 2009 : les premiers pèlerins sont partis","date":"2009-11-09","newspaper":"Sidwaya","country":"Burkina Faso","type":"articles"},{"id":"3115","title":"Hadj 2008 : 274 candidats ouvrent le vol","date":"2008-11-11","newspaper":"Sidwaya","country":"Burkina Faso","type":"articles"},{"id":"23282","title":"Hadj 2009 : les premiers pèlerins burkinabè sont partis","date":"2009-11-08","newspaper":"FasoZine","country":"Burkina Faso","type":"articles"}]},{"name":"Médine","lat":24.46861,"lng":39.61417,"country":"Saudi Arabia","articleCount":13,"articles":[{"id":"2365","title":"Hadj 2007 : les organisateurs contre le retour de l'État dans l'organisation","date":"2008-02-04","newspaper":"Le Pays","country":"Burkina Faso","type":"articles"},{"id":"2552","title":"518 pèlerins burkinabè pour le premier vol","date":"2010-11-03","newspaper":"Le Pays","country":"Burkina Faso","type":"articles"},{"id":"2599","title":"Hadj : des propositions pour une gestion saine et efficace","date":"2008-01-29","newspaper":"Le Pays","country":"Burkina Faso","type":"articles"},{"id":"2619","title":"Les premiers pèlerins ont décollé","date":"2009-11-08","newspaper":"Le Pays","country":"Burkina Faso","type":"articles"},{"id":"2720","title":"Hadj 2011 : 1er vol ce soir à 23h30","date":"2011-10-18","newspaper":"L'Observateur Paalga","country":"Burkina Faso","type":"articles"},{"id":"2725","title":"Hadj 2008 : premier test d'une « privatisation encadrée »","date":"2008-11-13","newspaper":"L'Observateur Paalga","country":"Burkina Faso","type":"articles"},{"id":"2743","title":"Hadj 2008 : le point des préparatifs","date":"2008-10-09","newspaper":"L'Observateur Paalga","country":"Burkina Faso","type":"articles"},{"id":"2788","title":"Hadj 2011 : triste sort pour 144 pèlerins recalés","date":"2011-10-25","newspaper":"L'Observateur Paalga","country":"Burkina Faso","type":"articles"},{"id":"2943","title":"Les premiers pèlerins de retour au bercail","date":"2010-12-13","newspaper":"Sidwaya","country":"Burkina Faso","type":"articles"},{"id":"3012","title":"Louis Yaméogo, coordonnateur de l'Oavp : \"Nos premiers pèlerins décollent aujourd'hui\"","date":"2008-11-12","newspaper":"Sidwaya","country":"Burkina Faso","type":"articles"},{"id":"3061","title":"Hadj édition 2010 : 1 million 193 mille F CFA pour le billet d'avion","date":"2010-09-14","newspaper":"Sidwaya","country":"Burkina Faso","type":"articles"},{"id":"3111","title":"Hadj 2009 : les premiers pèlerins sont partis","date":"2009-11-09","newspaper":"Sidwaya","country":"Burkina Faso","type":"articles"},{"id":"3195","title":"Hadj 2011 : départ des pèlerins aujourd'hui","date":"2011-10-18","newspaper":"Sidwaya","country":"Burkina Faso","type":"articles"}]},{"name":"Djeddah","lat":21.49012,"lng":39.18624,"country":"Saudi Arabia","articleCount":7,"articles":[{"id":"2285","title":"Des pèlerins interpellent le MATD sur leurs déboires","date":"2010-01-24","newspaper":"Le Pays","country":"Burkina Faso","type":"articles"},{"id":"2599","title":"Hadj : des propositions pour une gestion saine et efficace","date":"2008-01-29","newspaper":"Le Pays","country":"Burkina Faso","type":"articles"},{"id":"2725","title":"Hadj 2008 : premier test d'une « privatisation encadrée »","date":"2008-11-13","newspaper":"L'Observateur Paalga","country":"Burkina Faso","type":"articles"},{"id":"2943","title":"Les premiers pèlerins de retour au bercail","date":"2010-12-13","newspaper":"Sidwaya","country":"Burkina Faso","type":"articles"},{"id":"2946","title":"Hadj 2009 : une seule agence agréée pour l'organisation du pèlerinage","date":"2009-06-01","newspaper":"Sidwaya","country":"Burkina Faso","type":"articles"},{"id":"3036","title":"Les insuffisances du Hadj 2009 expliquées aux députés","date":"2010-03-29","newspaper":"Sidwaya","country":"Burkina Faso","type":"articles"},{"id":"3107","title":"518 pèlerins ouvrent le vol vers les lieux saints","date":"2010-11-04","newspaper":"Sidwaya","country":"Burkina Faso","type":"articles"}]},{"name":"Mali","lat":18.0,"lng":-2.0,"country":"Mali","articleCount":6,"articles":[{"id":"2256","title":"Organisation du Hadj 2011 : pour une concurrence au niveau du transport aérien","date":"2011-09-14","newspaper":"Le Pays","country":"Burkina Faso","type":"articles"},{"id":"2599","title":"Hadj : des propositions pour une gestion saine et efficace","date":"2008-01-29","newspaper":"Le Pays","country":"Burkina Faso","type":"articles"},{"id":"2720","title":"Hadj 2011 : 1er vol ce soir à 23h30","date":"2011-10-18","newspaper":"L'Observateur Paalga","country":"Burkina Faso","type":"articles"},{"id":"3036","title":"Les insuffisances du Hadj 2009 expliquées aux députés","date":"2010-03-29","newspaper":"Sidwaya","country":"Burkina Faso","type":"articles"},{"id":"3195","title":"Hadj 2011 : départ des pèlerins aujourd'hui","date":"2011-10-18","newspaper":"Sidwaya","country":"Burkina Faso","type":"articles"},{"id":"23344","title":"Hadj 2011 : «On ne peut pas donner un tel marché à un seul transporteur aérien»","date":"2011-11-01","newspaper":"FasoZine","country":"Burkina Faso","type":"articles"}]},{"name":"Côte d'Ivoire","lat":8.0,"lng":-5.5,"country":"Côte d'Ivoire","articleCount":4,"articles":[{"id":"2256","title":"Organisation du Hadj 2011 : pour une concurrence au niveau du transport aérien","date":"2011-09-14","newspaper":"Le Pays","country":"Burkina Faso","type":"articles"},{"id":"2599","title":"Hadj : des propositions pour une gestion saine et efficace","date":"2008-01-29","newspaper":"Le Pays","country":"Burkina Faso","type":"articles"},{"id":"3012","title":"Louis Yaméogo, coordonnateur de l'Oavp : \"Nos premiers pèlerins décollent aujourd'hui\"","date":"2008-11-12","newspaper":"Sidwaya","country":"Burkina Faso","type":"articles"},{"id":"3036","title":"Les insuffisances du Hadj 2009 expliquées aux députés","date":"2010-03-29","newspaper":"Sidwaya","country":"Burkina Faso","type":"articles"}]},{"name":"Ouahigouya","lat":13.58278,"lng":-2.42158,"country":"Burkina Faso","articleCount":4,"articles":[{"id":"2442","title":"Hadj 2007 : 2000 visas pour les Burkinabè","date":"2007-11-12","newspaper":"Le Pays","country":"Burkina Faso","type":"articles"},{"id":"2599","title":"Hadj : des propositions pour une gestion saine et efficace","date":"2008-01-29","newspaper":"Le Pays","country":"Burkina Faso","type":"articles"},{"id":"2743","title":"Hadj 2008 : le point des préparatifs","date":"2008-10-09","newspaper":"L'Observateur Paalga","country":"Burkina Faso","type":"articles"},{"id":"23281","title":"Hadj 2009 : déjà un millier de pèlerins inscrits","date":"2009-10-21","newspaper":"FasoZine","country":"Burkina Faso","type":"articles"}]},{"name":"Niger","lat":18.0,"lng":9.0,"country":"Niger","articleCount":3,"articles":[{"id":"2256","title":"Organisation du Hadj 2011 : pour une concurrence au niveau du transport aérien","date":"2011-09-14","newspaper":"Le Pays","country":"Burkina Faso","type":"articles"},{"id":"2599","title":"Hadj : des propositions pour une gestion saine et efficace","date":"2008-01-29","newspaper":"Le Pays","country":"Burkina Faso","type":"articles"},{"id":"3036","title":"Les insuffisances du Hadj 2009 expliquées aux députés","date":"2010-03-29","newspaper":"Sidwaya","country":"Burkina Faso","type":"articles"}]},{"name":"Kaaba","lat":21.4225,"lng":39.826167,"country":"Saudi Arabia","articleCount":3,"articles":[{"id":"2285","title":"Des pèlerins interpellent le MATD sur leurs déboires","date":"2010-01-24","newspaper":"Le Pays","country":"Burkina Faso","type":"articles"},{"id":"2426","title":"Le choix de STMB-Tours fait débat","date":"2010-10-06","newspaper":"Le Pays","country":"Burkina Faso","type":"articles"},{"id":"2949","title":"Hadj 2008 : 2 114 pèlerins burkinabè en terre sainte","date":"2008-12-05","newspaper":"Sidwaya","country":"Burkina Faso","type":"articles"}]},{"name":"Fada N'Gourma","lat":12.06157,"lng":0.35843,"country":"Burkina Faso","articleCount":3,"articles":[{"id":"2599","title":"Hadj : des propositions pour une gestion saine et efficace","date":"2008-01-29","newspaper":"Le Pays","country":"Burkina Faso","type":"articles"},{"id":"2743","title":"Hadj 2008 : le point des préparatifs","date":"2008-10-09","newspaper":"L'Observateur Paalga","country":"Burkina Faso","type":"articles"},{"id":"23281","title":"Hadj 2009 : déjà un millier de pèlerins inscrits","date":"2009-10-21","newspaper":"FasoZine","country":"Burkina Faso","type":"articles"}]},{"name":"Soudan","lat":16.0,"lng":30.0,"country":"Sudan","articleCount":2,"articles":[{"id":"2442","title":"Hadj 2007 : 2000 visas pour les Burkinabè","date":"2007-11-12","newspaper":"Le Pays","country":"Burkina Faso","type":"articles"},{"id":"12075","title":"Le CERFIste #13","date":"2010-12","newspaper":"Le CERFIste","country":"Burkina Faso","type":"publications"}]},{"name":"Gourcy","lat":13.20776,"lng":-2.35893,"country":"Burkina Faso","articleCount":2,"articles":[{"id":"2552","title":"518 pèlerins burkinabè pour le premier vol","date":"2010-11-03","newspaper":"Le Pays","country":"Burkina Faso","type":"articles"},{"id":"12075","title":"Le CERFIste #13","date":"2010-12","newspaper":"Le CERFIste","country":"Burkina Faso","type":"publications"}]},{"name":"Gambie","lat":13.5,"lng":-15.5,"country":"Gambia","articleCount":2,"articles":[{"id":"2720","title":"Hadj 2011 : 1er vol ce soir à 23h30","date":"2011-10-18","newspaper":"L'Observateur Paalga","country":"Burkina Faso","type":"articles"},{"id":"3195","title":"Hadj 2011 : départ des pèlerins aujourd'hui","date":"2011-10-18","newspaper":"Sidwaya","country":"Burkina Faso","type":"articles"}]},{"name":"Sya","lat":0,"lng":0,"country":"Unknown","articleCount":2,"articles":[{"id":"3010","title":"Pèlerinage 2009 : les péripéties d'un départ pour les lieux saints","date":"2009-11-11","newspaper":"Sidwaya","country":"Burkina Faso","type":"articles"},{"id":"3041","title":"Hadj 2007 : la première vague des pèlerins de retour à Sya","date":"2008-01-15","newspaper":"Sidwaya","country":"Burkina Faso","type":"articles"}]},{"name":"Sénégal","lat":14.5,"lng":-14.25,"country":"Senegal","articleCount":2,"articles":[{"id":"3012","title":"Louis Yaméogo, coordonnateur de l'Oavp : \"Nos premiers pèlerins décollent aujourd'hui\"","date":"2008-11-12","newspaper":"Sidwaya","country":"Burkina Faso","type":"articles"},{"id":"3036","title":"Les insuffisances du Hadj 2009 expliquées aux députés","date":"2010-03-29","newspaper":"Sidwaya","country":"Burkina Faso","type":"articles"}]},{"name":"Ghana","lat":8.1,"lng":-1.2,"country":"Ghana","articleCount":1,"articles":[{"id":"2256","title":"Organisation du Hadj 2011 : pour une concurrence au niveau du transport aérien","date":"2011-09-14","newspaper":"Le Pays","country":"Burkina Faso","type":"articles"}]},{"name":"Bénin","lat":9.5,"lng":2.25,"country":"Benin","articleCount":1,"articles":[{"id":"2256","title":"Organisation du Hadj 2011 : pour une concurrence au niveau du transport aérien","date":"2011-09-14","newspaper":"Le Pays","country":"Burkina Faso","type":"articles"}]},{"name":"Yako","lat":12.9591,"lng":-2.26075,"country":"Burkina Faso","articleCount":1,"articles":[{"id":"2599","title":"Hadj : des propositions pour une gestion saine et efficace","date":"2008-01-29","newspaper":"Le Pays","country":"Burkina Faso","type":"articles"}]},{"name":"Nigéria","lat":10.0,"lng":8.0,"country":"Nigeria","articleCount":1,"articles":[{"id":"2599","title":"Hadj : des propositions pour une gestion saine et efficace","date":"2008-01-29","newspaper":"Le Pays","country":"Burkina Faso","type":"articles"}]},{"name":"République centrafricaine","lat":6.7,"lng":20.9,"country":"Central African Rep.","articleCount":1,"articles":[{"id":"2599","title":"Hadj : des propositions pour une gestion saine et efficace","date":"2008-01-29","newspaper":"Le Pays","country":"Burkina Faso","type":"articles"}]},{"name":"Koubri","lat":12.1675,"lng":-1.35556,"country":"Burkina Faso","articleCount":1,"articles":[{"id":"2946","title":"Hadj 2009 : une seule agence agréée pour l'organisation du pèlerinage","date":"2009-06-01","newspaper":"Sidwaya","country":"Burkina Faso","type":"articles"}]},{"name":"Garango","lat":11.804722222222,"lng":-0.54888888888889,"country":"Burkina Faso","articleCount":1,"articles":[{"id":"2946","title":"Hadj 2009 : une seule agence agréée pour l'organisation du pèlerinage","date":"2009-06-01","newspaper":"Sidwaya","country":"Burkina Faso","type":"articles"}]},{"name":"Yatenga","lat":13.583333,"lng":-2.416667,"country":"Burkina Faso","articleCount":1,"articles":[{"id":"2949","title":"Hadj 2008 : 2 114 pèlerins burkinabè en terre sainte","date":"2008-12-05","newspaper":"Sidwaya","country":"Burkina Faso","type":"articles"}]},{"name":"Mont Arafat","lat":21.354831,"lng":39.983886,"country":"Saudi Arabia","articleCount":1,"articles":[{"id":"2949","title":"Hadj 2008 : 2 114 pèlerins burkinabè en terre sainte","date":"2008-12-05","newspaper":"Sidwaya","country":"Burkina Faso","type":"articles"}]},{"name":"France","lat":46.0,"lng":2.0,"country":"France","articleCount":1,"articles":[{"id":"3036","title":"Les insuffisances du Hadj 2009 expliquées aux députés","date":"2010-03-29","newspaper":"Sidwaya","country":"Burkina Faso","type":"articles"}]},{"name":"Dakar","lat":14.731944444444,"lng":-17.457222222222,"country":"Senegal","articleCount":1,"articles":[{"id":"3111","title":"Hadj 2009 : les premiers pèlerins sont partis","date":"2009-11-09","newspaper":"Sidwaya","country":"Burkina Faso","type":"articles"}]},{"name":"Ziniaré","lat":12.58186,"lng":-1.2971,"country":"Burkina Faso","articleCount":1,"articles":[{"id":"12075","title":"Le CERFIste #13","date":"2010-12","newspaper":"Le CERFIste","country":"Burkina Faso","type":"publications"}]},{"name":"Koweït","lat":29.5,"lng":47.75,"country":"Kuwait","articleCount":1,"articles":[{"id":"12075","title":"Le CERFIste #13","date":"2010-12","newspaper":"Le CERFIste","country":"Burkina Faso","type":"publications"}]},{"name":"Pakistan","lat":30.0,"lng":70.0,"country":"Pakistan","articleCount":1,"articles":[{"id":"12075","title":"Le CERFIste #13","date":"2010-12","newspaper":"Le CERFIste","country":"Burkina Faso","type":"publications"}]}]}